<?xml version="1.0" encoding="UTF-8" standalone="yes"?><response><appendix><airlines><airline><fs>VX</fs><iata>VX</iata><icao>VRD</icao><name>Virgin America</name><active>true</active></airline></airlines><airports><airport><fs>LAX</fs><iata>LAX</iata><icao>KLAX</icao><faa>LAX</faa><name>Los Angeles International Airport</name><street1>One World Way</street1><street2></street2><city>Los Angeles</city><cityCode>LAX</cityCode><stateCode>CA</stateCode><postalCode>90045-5803</postalCode><countryCode>US</countryCode><countryName>United States</countryName><regionName>North America</regionName><timeZoneRegionName>America/Los_Angeles</timeZoneRegionName><weatherZone>CAZ041</weatherZone><localTime>2013-08-09T01:00:59.495</localTime><utcOffsetHours>-7.0</utcOffsetHours><latitude>33.943399</latitude><longitude>-118.408279</longitude><elevationFeet>126</elevationFeet><classification>1</classification><active>true</active><delayIndexUrl>https://api.flightstats.com/flex/delayindex/rest/v1/json/airports/LAX?codeType=fs</delayIndexUrl><weatherUrl>https://api.flightstats.com/flex/weather/rest/v1/json/all/LAX?codeType=fs</weatherUrl></airport><airport><fs>JFK</fs><iata>JFK</iata><icao>KJFK</icao><faa>JFK</faa><name>John F. Kennedy International Airport</name><street1>JFK Airport</street1><city>New York</city><cityCode>NYC</cityCode><stateCode>NY</stateCode><postalCode>11430</postalCode><countryCode>US</countryCode><countryName>United States</countryName><regionName>North America</regionName><timeZoneRegionName>America/New_York</timeZoneRegionName><weatherZone>NYZ178</weatherZone><localTime>2013-08-09T04:00:59.495</localTime><utcOffsetHours>-4.0</utcOffsetHours><latitude>40.642335</latitude><longitude>-73.78817</longitude><elevationFeet>13</elevationFeet><classification>1</classification><active>true</active><delayIndexUrl>https://api.flightstats.com/flex/delayindex/rest/v1/json/airports/JFK?codeType=fs</delayIndexUrl><weatherUrl>https://api.flightstats.com/flex/weather/rest/v1/json/all/JFK?codeType=fs</weatherUrl></airport></airports></appendix><flightTracks><flightTrack><flightId>305334287</flightId><carrierFsCode>VX</carrierFsCode><flightNumber>406</flightNumber><callsign>VRD406</callsign><departureAirportFsCode>LAX</departureAirportFsCode><arrivalAirportFsCode>JFK</arrivalAirportFsCode><departureDate><dateLocal>2013-08-08T10:40:00.000</dateLocal><dateUtc>2013-08-08T17:40:00.000Z</dateUtc></departureDate><equipment>A320</equipment><delayMinutes>166</delayMinutes><bearing>237.93547441781578</bearing><heading>194.19042136118645</heading><positions><position><lon>-73.7300033569336</lon><lat>40.66999816894531</lat><speedMph>145</speedMph><altitudeFt>500</altitudeFt><source>ASDI</source><date>2013-08-09T01:26:11.000Z</date></position><position><lon>-73.72000122070312</lon><lat>40.70000076293945</lat><speedMph>158</speedMph><altitudeFt>1100</altitudeFt><source>ASDI</source><date>2013-08-09T01:25:11.000Z</date></position><position><lon>-73.68000030517578</lon><lat>40.72999954223633</lat><speedMph>194</speedMph><altitudeFt>1800</altitudeFt><source>ASDI</source><date>2013-08-09T01:24:11.000Z</date></position><position><lon>-73.6500015258789</lon><lat>40.77000045776367</lat><speedMph>200</speedMph><altitudeFt>2200</altitudeFt><source>ASDI</source><date>2013-08-09T01:23:11.000Z</date></position><position><lon>-73.62000274658203</lon><lat>40.79999923706055</lat><speedMph>200</speedMph><altitudeFt>2500</altitudeFt><source>ASDI</source><date>2013-08-09T01:22:11.000Z</date></position><position><lon>-73.56999969482422</lon><lat>40.83000183105469</lat><speedMph>200</speedMph><altitudeFt>3000</altitudeFt><source>ASDI</source><date>2013-08-09T01:21:11.000Z</date></position><position><lon>-73.5199966430664</lon><lat>40.849998474121094</lat><speedMph>214</speedMph><altitudeFt>3200</altitudeFt><source>ASDI</source><date>2013-08-09T01:20:11.000Z</date></position><position><lon>-73.44999694824219</lon><lat>40.849998474121094</lat><speedMph>241</speedMph><altitudeFt>3800</altitudeFt><source>ASDI</source><date>2013-08-09T01:19:11.000Z</date></position><position><lon>-73.37999725341797</lon><lat>40.81999969482422</lat><speedMph>281</speedMph><altitudeFt>4000</altitudeFt><source>ASDI</source><date>2013-08-09T01:18:11.000Z</date></position><position><lon>-73.3499984741211</lon><lat>40.779998779296875</lat><speedMph>270</speedMph><altitudeFt>4000</altitudeFt><source>ASDI</source><date>2013-08-09T01:17:42.000Z</date></position><position><lon>-73.37999725341797</lon><lat>40.75</lat><speedMph>280</speedMph><altitudeFt>4000</altitudeFt><source>ASDI</source><date>2013-08-09T01:17:11.000Z</date></position><position><lon>-73.37999725341797</lon><lat>40.70000076293945</lat><speedMph>270</speedMph><altitudeFt>4000</altitudeFt><source>ASDI</source><date>2013-08-09T01:16:44.000Z</date></position><position><lon>-73.4000015258789</lon><lat>40.68000030517578</lat><speedMph>282</speedMph><altitudeFt>4000</altitudeFt><source>ASDI</source><date>2013-08-09T01:16:11.000Z</date></position><position><lon>-73.41999816894531</lon><lat>40.650001525878906</lat><speedMph>270</speedMph><altitudeFt>4000</altitudeFt><source>ASDI</source><date>2013-08-09T01:15:43.000Z</date></position><position><lon>-73.43000030517578</lon><lat>40.630001068115234</lat><speedMph>282</speedMph><altitudeFt>4000</altitudeFt><source>ASDI</source><date>2013-08-09T01:15:11.000Z</date></position><position><lon>-73.44999694824219</lon><lat>40.58000183105469</lat><speedMph>276</speedMph><altitudeFt>4000</altitudeFt><source>ASDI</source><date>2013-08-09T01:14:43.000Z</date></position><position><lon>-73.47000122070312</lon><lat>40.56999969482422</lat><speedMph>280</speedMph><altitudeFt>4000</altitudeFt><source>ASDI</source><date>2013-08-09T01:14:11.000Z</date></position><position><lon>-73.47000122070312</lon><lat>40.52000045776367</lat><speedMph>276</speedMph><altitudeFt>4000</altitudeFt><source>ASDI</source><date>2013-08-09T01:13:42.000Z</date></position><position><lon>-73.5</lon><lat>40.5</lat><speedMph>283</speedMph><altitudeFt>4000</altitudeFt><source>ASDI</source><date>2013-08-09T01:13:11.000Z</date></position><position><lon>-73.5199966430664</lon><lat>40.45000076293945</lat><speedMph>282</speedMph><altitudeFt>4100</altitudeFt><source>ASDI</source><date>2013-08-09T01:12:41.000Z</date></position><position><lon>-73.52999877929688</lon><lat>40.43000030517578</lat><speedMph>281</speedMph><altitudeFt>4500</altitudeFt><source>ASDI</source><date>2013-08-09T01:12:11.000Z</date></position><position><lon>-73.55000305175781</lon><lat>40.400001525878906</lat><speedMph>296</speedMph><altitudeFt>5200</altitudeFt><source>ASDI</source><date>2013-08-09T01:11:43.000Z</date></position><position><lon>-73.58000183105469</lon><lat>40.369998931884766</lat><speedMph>299</speedMph><altitudeFt>5800</altitudeFt><source>ASDI</source><date>2013-08-09T01:11:11.000Z</date></position><position><lon>-73.5999984741211</lon><lat>40.33000183105469</lat><speedMph>339</speedMph><altitudeFt>6200</altitudeFt><source>ASDI</source><date>2013-08-09T01:10:43.000Z</date></position><position><lon>-73.62999725341797</lon><lat>40.29999923706055</lat><speedMph>330</speedMph><altitudeFt>6600</altitudeFt><source>ASDI</source><date>2013-08-09T01:10:11.000Z</date></position><position><lon>-73.6500015258789</lon><lat>40.27000045776367</lat><speedMph>353</speedMph><altitudeFt>7000</altitudeFt><source>ASDI</source><date>2013-08-09T01:09:42.000Z</date></position><position><lon>-73.68000030517578</lon><lat>40.22999954223633</lat><speedMph>354</speedMph><altitudeFt>7600</altitudeFt><source>ASDI</source><date>2013-08-09T01:09:11.000Z</date></position><position><lon>-73.69999694824219</lon><lat>40.18000030517578</lat><speedMph>346</speedMph><altitudeFt>8300</altitudeFt><source>ASDI</source><date>2013-08-09T01:08:42.000Z</date></position><position><lon>-73.7300033569336</lon><lat>40.16999816894531</lat><speedMph>357</speedMph><altitudeFt>8900</altitudeFt><source>ASDI</source><date>2013-08-09T01:08:11.000Z</date></position><position><lon>-73.75</lon><lat>40.119998931884766</lat><speedMph>312</speedMph><altitudeFt>9600</altitudeFt><source>ASDI</source><date>2013-08-09T01:07:44.000Z</date></position><position><lon>-73.77999877929688</lon><lat>40.08000183105469</lat><speedMph>361</speedMph><altitudeFt>10300</altitudeFt><source>ASDI</source><date>2013-08-09T01:07:11.000Z</date></position><position><lon>-73.80000305175781</lon><lat>40.029998779296875</lat><speedMph>169</speedMph><altitudeFt>10900</altitudeFt><source>ASDI</source><date>2013-08-09T01:06:44.000Z</date></position><position><lon>-73.83000183105469</lon><lat>40.0</lat><speedMph>373</speedMph><altitudeFt>11000</altitudeFt><source>ASDI</source><date>2013-08-09T01:06:11.000Z</date></position><position><lon>-73.87000274658203</lon><lat>39.970001220703125</lat><speedMph>168</speedMph><altitudeFt>11000</altitudeFt><source>ASDI</source><date>2013-08-09T01:05:43.000Z</date></position><position><lon>-73.93000030517578</lon><lat>39.97999954223633</lat><speedMph>327</speedMph><altitudeFt>11000</altitudeFt><source>ASDI</source><date>2013-08-09T01:05:11.000Z</date></position><position><lon>-73.94999694824219</lon><lat>40.0</lat><speedMph>201</speedMph><altitudeFt>11000</altitudeFt><source>ASDI</source><date>2013-08-09T01:04:44.000Z</date></position><position><lon>-73.94999694824219</lon><lat>40.04999923706055</lat><speedMph>281</speedMph><altitudeFt>11000</altitudeFt><source>ASDI</source><date>2013-08-09T01:04:11.000Z</date></position><position><lon>-73.91999816894531</lon><lat>40.06999969482422</lat><speedMph>191</speedMph><altitudeFt>11000</altitudeFt><source>ASDI</source><date>2013-08-09T01:03:43.000Z</date></position><position><lon>-73.8499984741211</lon><lat>40.029998779296875</lat><speedMph>338</speedMph><altitudeFt>11000</altitudeFt><source>ASDI</source><date>2013-08-09T01:02:44.000Z</date></position><position><lon>-73.87999725341797</lon><lat>39.97999954223633</lat><speedMph>386</speedMph><altitudeFt>11000</altitudeFt><source>ASDI</source><date>2013-08-09T01:01:44.000Z</date></position><position><lon>-73.94999694824219</lon><lat>39.900001525878906</lat><speedMph>413</speedMph><altitudeFt>12600</altitudeFt><source>ASDI</source><date>2013-08-09T01:00:45.000Z</date></position><position><lon>-74.02999877929688</lon><lat>39.83000183105469</lat><speedMph>429</speedMph><altitudeFt>13800</altitudeFt><source>ASDI</source><date>2013-08-09T00:59:43.000Z</date></position><position><lon>-74.12000274658203</lon><lat>39.72999954223633</lat><speedMph>441</speedMph><altitudeFt>15600</altitudeFt><source>ASDI</source><date>2013-08-09T00:58:42.000Z</date></position><position><lon>-74.18000030517578</lon><lat>39.650001525878906</lat><speedMph>434</speedMph><altitudeFt>17300</altitudeFt><source>ASDI</source><date>2013-08-09T00:57:42.000Z</date></position><position><lon>-74.2699966430664</lon><lat>39.56999969482422</lat><speedMph>413</speedMph><altitudeFt>18000</altitudeFt><source>ASDI</source><date>2013-08-09T00:56:44.000Z</date></position><position><lon>-74.31999969482422</lon><lat>39.47999954223633</lat><speedMph>396</speedMph><altitudeFt>18000</altitudeFt><source>ASDI</source><date>2013-08-09T00:55:42.000Z</date></position><position><lon>-74.4000015258789</lon><lat>39.369998931884766</lat><speedMph>252</speedMph><altitudeFt>18000</altitudeFt><source>ASDI</source><date>2013-08-09T00:54:42.000Z</date></position><position><lon>-74.44999694824219</lon><lat>39.27000045776367</lat><speedMph>223</speedMph><altitudeFt>17900</altitudeFt><source>ASDI</source><date>2013-08-09T00:53:42.000Z</date></position><position><lon>-74.41999816894531</lon><lat>39.22999954223633</lat><speedMph>258</speedMph><altitudeFt>18000</altitudeFt><source>ASDI</source><date>2013-08-09T00:53:16.000Z</date></position><position><lon>-74.37000274658203</lon><lat>39.20000076293945</lat><speedMph>330</speedMph><altitudeFt>18300</altitudeFt><source>ASDI</source><date>2013-08-09T00:52:44.000Z</date></position><position><lon>-74.31999969482422</lon><lat>39.220001220703125</lat><speedMph>285</speedMph><altitudeFt>18700</altitudeFt><source>ASDI</source><date>2013-08-09T00:52:15.000Z</date></position><position><lon>-74.2699966430664</lon><lat>39.27000045776367</lat><speedMph>338</speedMph><altitudeFt>19300</altitudeFt><source>ASDI</source><date>2013-08-09T00:51:43.000Z</date></position><position><lon>-74.2300033569336</lon><lat>39.29999923706055</lat><speedMph>264</speedMph><altitudeFt>19700</altitudeFt><source>ASDI</source><date>2013-08-09T00:51:15.000Z</date></position><position><lon>-74.22000122070312</lon><lat>39.349998474121094</lat><speedMph>425</speedMph><altitudeFt>20300</altitudeFt><source>ASDI</source><date>2013-08-09T00:50:43.000Z</date></position><position><lon>-74.22000122070312</lon><lat>39.380001068115234</lat><speedMph>327</speedMph><altitudeFt>20700</altitudeFt><source>ASDI</source><date>2013-08-09T00:50:14.000Z</date></position><position><lon>-74.25</lon><lat>39.41999816894531</lat><speedMph>509</speedMph><altitudeFt>21100</altitudeFt><source>ASDI</source><date>2013-08-09T00:49:42.000Z</date></position><position><lon>-74.31999969482422</lon><lat>39.45000076293945</lat><speedMph>411</speedMph><altitudeFt>21600</altitudeFt><source>ASDI</source><date>2013-08-09T00:49:17.000Z</date></position><position><lon>-74.43000030517578</lon><lat>39.41999816894531</lat><speedMph>430</speedMph><altitudeFt>22700</altitudeFt><source>ASDI</source><date>2013-08-09T00:48:16.000Z</date></position><position><lon>-74.5199966430664</lon><lat>39.33000183105469</lat><speedMph>444</speedMph><altitudeFt>23600</altitudeFt><source>ASDI</source><date>2013-08-09T00:47:15.000Z</date></position><position><lon>-74.58000183105469</lon><lat>39.25</lat><speedMph>467</speedMph><altitudeFt>24500</altitudeFt><source>ASDI</source><date>2013-08-09T00:46:15.000Z</date></position><position><lon>-74.66999816894531</lon><lat>39.150001525878906</lat><speedMph>484</speedMph><altitudeFt>25500</altitudeFt><source>ASDI</source><date>2013-08-09T00:45:16.000Z</date></position><position><lon>-74.75</lon><lat>39.06999969482422</lat><speedMph>484</speedMph><altitudeFt>26800</altitudeFt><source>ASDI</source><date>2013-08-09T00:44:16.000Z</date></position><position><lon>-74.83000183105469</lon><lat>38.970001220703125</lat><speedMph>479</speedMph><altitudeFt>29300</altitudeFt><source>ASDI</source><date>2013-08-09T00:43:15.000Z</date></position><position><lon>-74.91999816894531</lon><lat>38.869998931884766</lat><speedMph>473</speedMph><altitudeFt>31700</altitudeFt><source>ASDI</source><date>2013-08-09T00:42:15.000Z</date></position><position><lon>-75.0</lon><lat>38.77000045776367</lat><speedMph>473</speedMph><altitudeFt>34300</altitudeFt><source>ASDI</source><date>2013-08-09T00:41:15.000Z</date></position><position><lon>-75.06999969482422</lon><lat>38.66999816894531</lat><speedMph>484</speedMph><altitudeFt>36400</altitudeFt><source>ASDI</source><date>2013-08-09T00:40:14.000Z</date></position><position><lon>-75.1500015258789</lon><lat>38.56999969482422</lat><speedMph>484</speedMph><altitudeFt>37000</altitudeFt><source>ASDI</source><date>2013-08-09T00:39:15.000Z</date></position><position><lon>-75.25</lon><lat>38.47999954223633</lat><speedMph>479</speedMph><altitudeFt>37000</altitudeFt><source>ASDI</source><date>2013-08-09T00:38:15.000Z</date></position><position><lon>-75.33000183105469</lon><lat>38.380001068115234</lat><speedMph>479</speedMph><altitudeFt>37000</altitudeFt><source>ASDI</source><date>2013-08-09T00:37:14.000Z</date></position><position><lon>-75.43000030517578</lon><lat>38.279998779296875</lat><speedMph>466</speedMph><altitudeFt>36900</altitudeFt><source>ASDI</source><date>2013-08-09T00:36:16.000Z</date></position><position><lon>-75.5</lon><lat>38.20000076293945</lat><speedMph>466</speedMph><altitudeFt>37000</altitudeFt><source>ASDI</source><date>2013-08-09T00:35:15.000Z</date></position><position><lon>-75.5999984741211</lon><lat>38.119998931884766</lat><speedMph>473</speedMph><altitudeFt>37000</altitudeFt><source>ASDI</source><date>2013-08-09T00:34:15.000Z</date></position><position><lon>-75.69999694824219</lon><lat>38.02000045776367</lat><speedMph>473</speedMph><altitudeFt>37000</altitudeFt><source>ASDI</source><date>2013-08-09T00:33:14.000Z</date></position><position><lon>-75.81999969482422</lon><lat>37.93000030517578</lat><speedMph>494</speedMph><altitudeFt>37000</altitudeFt><source>ASDI</source><date>2013-08-09T00:32:16.000Z</date></position><position><lon>-75.93000030517578</lon><lat>37.900001525878906</lat><speedMph>501</speedMph><altitudeFt>37000</altitudeFt><source>ASDI</source><date>2013-08-09T00:31:15.000Z</date></position><position><lon>-76.08000183105469</lon><lat>37.849998474121094</lat><speedMph>501</speedMph><altitudeFt>37000</altitudeFt><source>ASDI</source><date>2013-08-09T00:30:14.000Z</date></position><position><lon>-76.22000122070312</lon><lat>37.81999969482422</lat><speedMph>495</speedMph><altitudeFt>37000</altitudeFt><source>ASDI</source><date>2013-08-09T00:29:16.000Z</date></position><position><lon>-76.37000274658203</lon><lat>37.77000045776367</lat><speedMph>502</speedMph><altitudeFt>36900</altitudeFt><source>ASDI</source><date>2013-08-09T00:28:15.000Z</date></position><position><lon>-76.5</lon><lat>37.720001220703125</lat><speedMph>502</speedMph><altitudeFt>37000</altitudeFt><source>ASDI</source><date>2013-08-09T00:27:15.000Z</date></position><position><lon>-76.6500015258789</lon><lat>37.68000030517578</lat><speedMph>509</speedMph><altitudeFt>37000</altitudeFt><source>ASDI</source><date>2013-08-09T00:26:14.000Z</date></position><position><lon>-76.77999877929688</lon><lat>37.630001068115234</lat><speedMph>514</speedMph><altitudeFt>37000</altitudeFt><source>ASDI</source><date>2013-08-09T00:25:16.000Z</date></position><position><lon>-76.93000030517578</lon><lat>37.58000183105469</lat><speedMph>509</speedMph><altitudeFt>37000</altitudeFt><source>ASDI</source><date>2013-08-09T00:24:15.000Z</date></position><position><lon>-77.08000183105469</lon><lat>37.54999923706055</lat><speedMph>509</speedMph><altitudeFt>37000</altitudeFt><source>ASDI</source><date>2013-08-09T00:23:14.000Z</date></position><position><lon>-77.2300033569336</lon><lat>37.5</lat><speedMph>529</speedMph><altitudeFt>36900</altitudeFt><source>ASDI</source><date>2013-08-09T00:22:14.000Z</date></position><position><lon>-77.37999725341797</lon><lat>37.47999954223633</lat><speedMph>529</speedMph><altitudeFt>37000</altitudeFt><source>ASDI</source><date>2013-08-09T00:21:15.000Z</date></position><position><lon>-77.55000305175781</lon><lat>37.5</lat><speedMph>529</speedMph><altitudeFt>37000</altitudeFt><source>ASDI</source><date>2013-08-09T00:20:15.000Z</date></position><position><lon>-77.69999694824219</lon><lat>37.52000045776367</lat><speedMph>542</speedMph><altitudeFt>37000</altitudeFt><source>ASDI</source><date>2013-08-09T00:19:17.000Z</date></position><position><lon>-77.87000274658203</lon><lat>37.529998779296875</lat><speedMph>542</speedMph><altitudeFt>37000</altitudeFt><source>ASDI</source><date>2013-08-09T00:18:17.000Z</date></position><position><lon>-78.0199966430664</lon><lat>37.58000183105469</lat><speedMph>542</speedMph><altitudeFt>37000</altitudeFt><source>ASDI</source><date>2013-08-09T00:17:16.000Z</date></position><position><lon>-78.18000030517578</lon><lat>37.630001068115234</lat><speedMph>536</speedMph><altitudeFt>37000</altitudeFt><source>ASDI</source><date>2013-08-09T00:16:16.000Z</date></position><position><lon>-78.33000183105469</lon><lat>37.68000030517578</lat><speedMph>536</speedMph><altitudeFt>37000</altitudeFt><source>ASDI</source><date>2013-08-09T00:15:15.000Z</date></position><position><lon>-78.4800033569336</lon><lat>37.720001220703125</lat><speedMph>536</speedMph><altitudeFt>37000</altitudeFt><source>ASDI</source><date>2013-08-09T00:14:14.000Z</date></position><position><lon>-78.62999725341797</lon><lat>37.77000045776367</lat><speedMph>536</speedMph><altitudeFt>37000</altitudeFt><source>ASDI</source><date>2013-08-09T00:13:14.000Z</date></position><position><lon>-78.77999877929688</lon><lat>37.79999923706055</lat><speedMph>536</speedMph><altitudeFt>37000</altitudeFt><source>ASDI</source><date>2013-08-09T00:12:16.000Z</date></position><position><lon>-78.94999694824219</lon><lat>37.849998474121094</lat><speedMph>542</speedMph><altitudeFt>37000</altitudeFt><source>ASDI</source><date>2013-08-09T00:11:16.000Z</date></position><position><lon>-79.05000305175781</lon><lat>37.880001068115234</lat><speedMph>537</speedMph><altitudeFt>37000</altitudeFt><source>ASDI</source><date>2013-08-09T00:10:37.000Z</date></position><position><lon>-79.0999984741211</lon><lat>37.900001525878906</lat><speedMph>548</speedMph><altitudeFt>37000</altitudeFt><source>ASDI</source><date>2013-08-09T00:10:15.000Z</date></position><position><lon>-79.22000122070312</lon><lat>37.91999816894531</lat><speedMph>542</speedMph><altitudeFt>37000</altitudeFt><source>ASDI</source><date>2013-08-09T00:09:36.000Z</date></position><position><lon>-79.27999877929688</lon><lat>37.93000030517578</lat><speedMph>542</speedMph><altitudeFt>37000</altitudeFt><source>ASDI</source><date>2013-08-09T00:09:15.000Z</date></position><position><lon>-79.37999725341797</lon><lat>37.95000076293945</lat><speedMph>544</speedMph><altitudeFt>37000</altitudeFt><source>ASDI</source><date>2013-08-09T00:08:34.000Z</date></position><position><lon>-79.43000030517578</lon><lat>37.95000076293945</lat><speedMph>542</speedMph><altitudeFt>37000</altitudeFt><source>ASDI</source><date>2013-08-09T00:08:17.000Z</date></position><position><lon>-79.52999877929688</lon><lat>37.970001220703125</lat><speedMph>545</speedMph><altitudeFt>37000</altitudeFt><source>ASDI</source><date>2013-08-09T00:07:33.000Z</date></position><position><lon>-79.5999984741211</lon><lat>37.97999954223633</lat><speedMph>542</speedMph><altitudeFt>37000</altitudeFt><source>ASDI</source><date>2013-08-09T00:07:16.000Z</date></position><position><lon>-79.69999694824219</lon><lat>38.0</lat><speedMph>549</speedMph><altitudeFt>37000</altitudeFt><source>ASDI</source><date>2013-08-09T00:06:31.000Z</date></position><position><lon>-79.7699966430664</lon><lat>38.02000045776367</lat><speedMph>542</speedMph><altitudeFt>37000</altitudeFt><source>ASDI</source><date>2013-08-09T00:06:16.000Z</date></position><position><lon>-79.87999725341797</lon><lat>38.029998779296875</lat><speedMph>551</speedMph><altitudeFt>37000</altitudeFt><source>ASDI</source><date>2013-08-09T00:05:30.000Z</date></position><position><lon>-79.93000030517578</lon><lat>38.029998779296875</lat><speedMph>549</speedMph><altitudeFt>37000</altitudeFt><source>ASDI</source><date>2013-08-09T00:05:15.000Z</date></position><position><lon>-80.05000305175781</lon><lat>38.06999969482422</lat><speedMph>554</speedMph><altitudeFt>37000</altitudeFt><source>ASDI</source><date>2013-08-09T00:04:28.000Z</date></position><position><lon>-80.08000183105469</lon><lat>38.06999969482422</lat><speedMph>542</speedMph><altitudeFt>37000</altitudeFt><source>ASDI</source><date>2013-08-09T00:04:14.000Z</date></position><position><lon>-80.2300033569336</lon><lat>38.099998474121094</lat><speedMph>554</speedMph><altitudeFt>37000</altitudeFt><source>ASDI</source><date>2013-08-09T00:03:26.000Z</date></position><position><lon>-80.25</lon><lat>38.099998474121094</lat><speedMph>548</speedMph><altitudeFt>37000</altitudeFt><source>ASDI</source><date>2013-08-09T00:03:16.000Z</date></position><position><lon>-80.41999816894531</lon><lat>38.119998931884766</lat><speedMph>548</speedMph><altitudeFt>37000</altitudeFt><source>ASDI</source><date>2013-08-09T00:02:16.000Z</date></position><position><lon>-80.43000030517578</lon><lat>38.130001068115234</lat><speedMph>555</speedMph><altitudeFt>37000</altitudeFt><source>ASDI</source><date>2013-08-09T00:02:13.000Z</date></position><position><lon>-80.58000183105469</lon><lat>38.150001525878906</lat><speedMph>548</speedMph><altitudeFt>37000</altitudeFt><source>ASDI</source><date>2013-08-09T00:01:15.000Z</date></position><position><lon>-80.5999984741211</lon><lat>38.150001525878906</lat><speedMph>549</speedMph><altitudeFt>37000</altitudeFt><source>ASDI</source><date>2013-08-09T00:01:11.000Z</date></position><position><lon>-80.7699966430664</lon><lat>38.18000030517578</lat><speedMph>545</speedMph><altitudeFt>37000</altitudeFt><source>ASDI</source><date>2013-08-09T00:00:10.000Z</date></position><position><lon>-80.80000305175781</lon><lat>38.18000030517578</lat><speedMph>542</speedMph><altitudeFt>37000</altitudeFt><source>ASDI</source><date>2013-08-09T00:00:02.000Z</date></position><position><lon>-80.93000030517578</lon><lat>38.220001220703125</lat><speedMph>540</speedMph><altitudeFt>37200</altitudeFt><source>ASDI</source><date>2013-08-08T23:59:08.000Z</date></position><position><lon>-80.94999694824219</lon><lat>38.220001220703125</lat><speedMph>542</speedMph><altitudeFt>37300</altitudeFt><source>ASDI</source><date>2013-08-08T23:59:04.000Z</date></position><position><lon>-81.0999984741211</lon><lat>38.22999954223633</lat><speedMph>549</speedMph><altitudeFt>37800</altitudeFt><source>ASDI</source><date>2013-08-08T23:58:07.000Z</date></position><position><lon>-81.1500015258789</lon><lat>38.25</lat><speedMph>548</speedMph><altitudeFt>38000</altitudeFt><source>ASDI</source><date>2013-08-08T23:58:03.000Z</date></position><position><lon>-81.25</lon><lat>38.27000045776367</lat><speedMph>558</speedMph><altitudeFt>38000</altitudeFt><source>ASDI</source><date>2013-08-08T23:57:06.000Z</date></position><position><lon>-81.27999877929688</lon><lat>38.27000045776367</lat><speedMph>554</speedMph><altitudeFt>38000</altitudeFt><source>ASDI</source><date>2013-08-08T23:57:02.000Z</date></position><position><lon>-81.41999816894531</lon><lat>38.279998779296875</lat><speedMph>557</speedMph><altitudeFt>38000</altitudeFt><source>ASDI</source><date>2013-08-08T23:56:04.000Z</date></position><position><lon>-81.43000030517578</lon><lat>38.279998779296875</lat><speedMph>545</speedMph><altitudeFt>38000</altitudeFt><source>ASDI</source><date>2013-08-08T23:56:04.000Z</date></position><position><lon>-81.62000274658203</lon><lat>38.31999969482422</lat><speedMph>551</speedMph><altitudeFt>37900</altitudeFt><source>ASDI</source><date>2013-08-08T23:55:02.000Z</date></position><position><lon>-81.5999984741211</lon><lat>38.31999969482422</lat><speedMph>545</speedMph><altitudeFt>37900</altitudeFt><source>ASDI</source><date>2013-08-08T23:55:02.000Z</date></position><position><lon>-81.7699966430664</lon><lat>38.33000183105469</lat><speedMph>557</speedMph><altitudeFt>38000</altitudeFt><source>ASDI</source><date>2013-08-08T23:54:05.000Z</date></position><position><lon>-81.77999877929688</lon><lat>38.349998474121094</lat><speedMph>554</speedMph><altitudeFt>38000</altitudeFt><source>ASDI</source><date>2013-08-08T23:54:01.000Z</date></position><position><lon>-81.94999694824219</lon><lat>38.369998931884766</lat><speedMph>564</speedMph><altitudeFt>38000</altitudeFt><source>ASDI</source><date>2013-08-08T23:52:59.000Z</date></position><position><lon>-82.12000274658203</lon><lat>38.400001525878906</lat><speedMph>564</speedMph><altitudeFt>38000</altitudeFt><source>ASDI</source><date>2013-08-08T23:51:57.000Z</date></position><position><lon>-82.27999877929688</lon><lat>38.43000030517578</lat><speedMph>565</speedMph><altitudeFt>38000</altitudeFt><source>ASDI</source><date>2013-08-08T23:50:56.000Z</date></position><position><lon>-82.47000122070312</lon><lat>38.45000076293945</lat><speedMph>562</speedMph><altitudeFt>38000</altitudeFt><source>ASDI</source><date>2013-08-08T23:49:54.000Z</date></position><position><lon>-82.6500015258789</lon><lat>38.47999954223633</lat><speedMph>558</speedMph><altitudeFt>38000</altitudeFt><source>ASDI</source><date>2013-08-08T23:48:52.000Z</date></position><position><lon>-82.81999969482422</lon><lat>38.5</lat><speedMph>557</speedMph><altitudeFt>38000</altitudeFt><source>ASDI</source><date>2013-08-08T23:47:51.000Z</date></position><position><lon>-82.9800033569336</lon><lat>38.529998779296875</lat><speedMph>554</speedMph><altitudeFt>38000</altitudeFt><source>ASDI</source><date>2013-08-08T23:46:49.000Z</date></position><position><lon>-83.1500015258789</lon><lat>38.54999923706055</lat><speedMph>557</speedMph><altitudeFt>38000</altitudeFt><source>ASDI</source><date>2013-08-08T23:45:47.000Z</date></position><position><lon>-83.33000183105469</lon><lat>38.58000183105469</lat><speedMph>558</speedMph><altitudeFt>38000</altitudeFt><source>ASDI</source><date>2013-08-08T23:44:46.000Z</date></position><position><lon>-83.5</lon><lat>38.599998474121094</lat><speedMph>557</speedMph><altitudeFt>38000</altitudeFt><source>ASDI</source><date>2013-08-08T23:43:44.000Z</date></position><position><lon>-83.68000030517578</lon><lat>38.650001525878906</lat><speedMph>549</speedMph><altitudeFt>38000</altitudeFt><source>ASDI</source><date>2013-08-08T23:42:42.000Z</date></position><position><lon>-83.83000183105469</lon><lat>38.70000076293945</lat><speedMph>545</speedMph><altitudeFt>38000</altitudeFt><source>ASDI</source><date>2013-08-08T23:41:41.000Z</date></position><position><lon>-84.0</lon><lat>38.75</lat><speedMph>550</speedMph><altitudeFt>38000</altitudeFt><source>ASDI</source><date>2013-08-08T23:40:39.000Z</date></position><position><lon>-84.1500015258789</lon><lat>38.79999923706055</lat><speedMph>551</speedMph><altitudeFt>38000</altitudeFt><source>ASDI</source><date>2013-08-08T23:39:37.000Z</date></position><position><lon>-84.31999969482422</lon><lat>38.849998474121094</lat><speedMph>550</speedMph><altitudeFt>38000</altitudeFt><source>ASDI</source><date>2013-08-08T23:38:36.000Z</date></position><position><lon>-84.47000122070312</lon><lat>38.900001525878906</lat><speedMph>554</speedMph><altitudeFt>38000</altitudeFt><source>ASDI</source><date>2013-08-08T23:37:34.000Z</date></position><position><lon>-84.6500015258789</lon><lat>38.970001220703125</lat><speedMph>551</speedMph><altitudeFt>38000</altitudeFt><source>ASDI</source><date>2013-08-08T23:36:32.000Z</date></position><position><lon>-84.81999969482422</lon><lat>39.02000045776367</lat><speedMph>548</speedMph><altitudeFt>38000</altitudeFt><source>ASDI</source><date>2013-08-08T23:35:30.000Z</date></position><position><lon>-84.97000122070312</lon><lat>39.06999969482422</lat><speedMph>550</speedMph><altitudeFt>38000</altitudeFt><source>ASDI</source><date>2013-08-08T23:34:29.000Z</date></position><position><lon>-85.12000274658203</lon><lat>39.119998931884766</lat><speedMph>552</speedMph><altitudeFt>38000</altitudeFt><source>ASDI</source><date>2013-08-08T23:33:27.000Z</date></position><position><lon>-85.31999969482422</lon><lat>39.16999816894531</lat><speedMph>548</speedMph><altitudeFt>38000</altitudeFt><source>ASDI</source><date>2013-08-08T23:32:25.000Z</date></position><position><lon>-85.47000122070312</lon><lat>39.220001220703125</lat><speedMph>550</speedMph><altitudeFt>38000</altitudeFt><source>ASDI</source><date>2013-08-08T23:31:23.000Z</date></position><position><lon>-85.62999725341797</lon><lat>39.27000045776367</lat><speedMph>545</speedMph><altitudeFt>38000</altitudeFt><source>ASDI</source><date>2013-08-08T23:30:22.000Z</date></position><position><lon>-85.77999877929688</lon><lat>39.31999969482422</lat><speedMph>547</speedMph><altitudeFt>38000</altitudeFt><source>ASDI</source><date>2013-08-08T23:29:20.000Z</date></position><position><lon>-85.94999694824219</lon><lat>39.369998931884766</lat><speedMph>547</speedMph><altitudeFt>37800</altitudeFt><source>ASDI</source><date>2013-08-08T23:28:18.000Z</date></position><position><lon>-86.0999984741211</lon><lat>39.400001525878906</lat><speedMph>550</speedMph><altitudeFt>37200</altitudeFt><source>ASDI</source><date>2013-08-08T23:27:16.000Z</date></position><position><lon>-86.30000305175781</lon><lat>39.470001220703125</lat><speedMph>552</speedMph><altitudeFt>37000</altitudeFt><source>ASDI</source><date>2013-08-08T23:26:14.000Z</date></position><position><lon>-86.44999694824219</lon><lat>39.52000045776367</lat><speedMph>551</speedMph><altitudeFt>37000</altitudeFt><source>ASDI</source><date>2013-08-08T23:25:13.000Z</date></position><position><lon>-86.5999984741211</lon><lat>39.54999923706055</lat><speedMph>549</speedMph><altitudeFt>37000</altitudeFt><source>ASDI</source><date>2013-08-08T23:24:11.000Z</date></position><position><lon>-86.7699966430664</lon><lat>39.599998474121094</lat><speedMph>548</speedMph><altitudeFt>37000</altitudeFt><source>ASDI</source><date>2013-08-08T23:23:09.000Z</date></position><position><lon>-86.93000030517578</lon><lat>39.650001525878906</lat><speedMph>545</speedMph><altitudeFt>36900</altitudeFt><source>ASDI</source><date>2013-08-08T23:22:07.000Z</date></position><position><lon>-87.12000274658203</lon><lat>39.70000076293945</lat><speedMph>548</speedMph><altitudeFt>37000</altitudeFt><source>ASDI</source><date>2013-08-08T23:21:05.000Z</date></position><position><lon>-87.2699966430664</lon><lat>39.75</lat><speedMph>559</speedMph><altitudeFt>37000</altitudeFt><source>ASDI</source><date>2013-08-08T23:20:04.000Z</date></position><position><lon>-87.44999694824219</lon><lat>39.77000045776367</lat><speedMph>558</speedMph><altitudeFt>37000</altitudeFt><source>ASDI</source><date>2013-08-08T23:19:02.000Z</date></position><position><lon>-87.55000305175781</lon><lat>39.77000045776367</lat><speedMph>572</speedMph><altitudeFt>37000</altitudeFt><source>ASDI</source><date>2013-08-08T23:18:27.000Z</date></position><position><lon>-87.62000274658203</lon><lat>39.75</lat><speedMph>566</speedMph><altitudeFt>37000</altitudeFt><source>ASDI</source><date>2013-08-08T23:18:00.000Z</date></position><position><lon>-87.7300033569336</lon><lat>39.75</lat><speedMph>563</speedMph><altitudeFt>37000</altitudeFt><source>ASDI</source><date>2013-08-08T23:17:25.000Z</date></position><position><lon>-87.80000305175781</lon><lat>39.75</lat><speedMph>570</speedMph><altitudeFt>37000</altitudeFt><source>ASDI</source><date>2013-08-08T23:16:58.000Z</date></position><position><lon>-87.91999816894531</lon><lat>39.75</lat><speedMph>563</speedMph><altitudeFt>37000</altitudeFt><source>ASDI</source><date>2013-08-08T23:16:23.000Z</date></position><position><lon>-87.9800033569336</lon><lat>39.72999954223633</lat><speedMph>567</speedMph><altitudeFt>37000</altitudeFt><source>ASDI</source><date>2013-08-08T23:15:56.000Z</date></position><position><lon>-88.08000183105469</lon><lat>39.72999954223633</lat><speedMph>565</speedMph><altitudeFt>37000</altitudeFt><source>ASDI</source><date>2013-08-08T23:15:21.000Z</date></position><position><lon>-88.18000030517578</lon><lat>39.72999954223633</lat><speedMph>567</speedMph><altitudeFt>37000</altitudeFt><source>ASDI</source><date>2013-08-08T23:14:55.000Z</date></position><position><lon>-88.2699966430664</lon><lat>39.72999954223633</lat><speedMph>564</speedMph><altitudeFt>37000</altitudeFt><source>ASDI</source><date>2013-08-08T23:14:19.000Z</date></position><position><lon>-88.37000274658203</lon><lat>39.720001220703125</lat><speedMph>563</speedMph><altitudeFt>37000</altitudeFt><source>ASDI</source><date>2013-08-08T23:13:53.000Z</date></position><position><lon>-88.4800033569336</lon><lat>39.720001220703125</lat><speedMph>559</speedMph><altitudeFt>37000</altitudeFt><source>ASDI</source><date>2013-08-08T23:13:17.000Z</date></position><position><lon>-88.52999877929688</lon><lat>39.720001220703125</lat><speedMph>563</speedMph><altitudeFt>37000</altitudeFt><source>ASDI</source><date>2013-08-08T23:12:51.000Z</date></position><position><lon>-88.6500015258789</lon><lat>39.70000076293945</lat><speedMph>564</speedMph><altitudeFt>37000</altitudeFt><source>ASDI</source><date>2013-08-08T23:12:15.000Z</date></position><position><lon>-88.72000122070312</lon><lat>39.70000076293945</lat><speedMph>568</speedMph><altitudeFt>37000</altitudeFt><source>ASDI</source><date>2013-08-08T23:11:49.000Z</date></position><position><lon>-88.83000183105469</lon><lat>39.70000076293945</lat><speedMph>565</speedMph><altitudeFt>37000</altitudeFt><source>ASDI</source><date>2013-08-08T23:11:13.000Z</date></position><position><lon>-88.9000015258789</lon><lat>39.68000030517578</lat><speedMph>565</speedMph><altitudeFt>37000</altitudeFt><source>ASDI</source><date>2013-08-08T23:10:47.000Z</date></position><position><lon>-89.0</lon><lat>39.68000030517578</lat><speedMph>570</speedMph><altitudeFt>37000</altitudeFt><source>ASDI</source><date>2013-08-08T23:10:11.000Z</date></position><position><lon>-89.06999969482422</lon><lat>39.68000030517578</lat><speedMph>573</speedMph><altitudeFt>37000</altitudeFt><source>ASDI</source><date>2013-08-08T23:09:46.000Z</date></position><position><lon>-89.18000030517578</lon><lat>39.68000030517578</lat><speedMph>573</speedMph><altitudeFt>37000</altitudeFt><source>ASDI</source><date>2013-08-08T23:09:09.000Z</date></position><position><lon>-89.27999877929688</lon><lat>39.66999816894531</lat><speedMph>574</speedMph><altitudeFt>37000</altitudeFt><source>ASDI</source><date>2013-08-08T23:08:44.000Z</date></position><position><lon>-89.37000274658203</lon><lat>39.66999816894531</lat><speedMph>573</speedMph><altitudeFt>37000</altitudeFt><source>ASDI</source><date>2013-08-08T23:08:07.000Z</date></position><position><lon>-89.47000122070312</lon><lat>39.650001525878906</lat><speedMph>577</speedMph><altitudeFt>37000</altitudeFt><source>ASDI</source><date>2013-08-08T23:07:42.000Z</date></position><position><lon>-89.55000305175781</lon><lat>39.650001525878906</lat><speedMph>578</speedMph><altitudeFt>37000</altitudeFt><source>ASDI</source><date>2013-08-08T23:07:05.000Z</date></position><position><lon>-89.62999725341797</lon><lat>39.650001525878906</lat><speedMph>577</speedMph><altitudeFt>37000</altitudeFt><source>ASDI</source><date>2013-08-08T23:06:40.000Z</date></position><position><lon>-89.7699966430664</lon><lat>39.630001068115234</lat><speedMph>575</speedMph><altitudeFt>37000</altitudeFt><source>ASDI</source><date>2013-08-08T23:06:03.000Z</date></position><position><lon>-89.93000030517578</lon><lat>39.619998931884766</lat><speedMph>577</speedMph><altitudeFt>37000</altitudeFt><source>ASDI</source><date>2013-08-08T23:05:01.000Z</date></position><position><lon>-90.12000274658203</lon><lat>39.599998474121094</lat><speedMph>577</speedMph><altitudeFt>37000</altitudeFt><source>ASDI</source><date>2013-08-08T23:03:59.000Z</date></position><position><lon>-90.47000122070312</lon><lat>39.54999923706055</lat><speedMph>575</speedMph><altitudeFt>37000</altitudeFt><source>ASDI</source><date>2013-08-08T23:01:54.000Z</date></position><position><lon>-90.6500015258789</lon><lat>39.52000045776367</lat><speedMph>571</speedMph><altitudeFt>37000</altitudeFt><source>ASDI</source><date>2013-08-08T23:00:52.000Z</date></position><position><lon>-90.83000183105469</lon><lat>39.5</lat><speedMph>567</speedMph><altitudeFt>37000</altitudeFt><source>ASDI</source><date>2013-08-08T22:59:50.000Z</date></position><position><lon>-91.02999877929688</lon><lat>39.470001220703125</lat><speedMph>577</speedMph><altitudeFt>37000</altitudeFt><source>ASDI</source><date>2013-08-08T22:58:48.000Z</date></position><position><lon>-91.22000122070312</lon><lat>39.43000030517578</lat><speedMph>575</speedMph><altitudeFt>37000</altitudeFt><source>ASDI</source><date>2013-08-08T22:57:46.000Z</date></position><position><lon>-91.37999725341797</lon><lat>39.41999816894531</lat><speedMph>574</speedMph><altitudeFt>37000</altitudeFt><source>ASDI</source><date>2013-08-08T22:56:44.000Z</date></position><position><lon>-91.56999969482422</lon><lat>39.380001068115234</lat><speedMph>574</speedMph><altitudeFt>37000</altitudeFt><source>ASDI</source><date>2013-08-08T22:55:42.000Z</date></position><position><lon>-91.75</lon><lat>39.349998474121094</lat><speedMph>570</speedMph><altitudeFt>37000</altitudeFt><source>ASDI</source><date>2013-08-08T22:54:40.000Z</date></position><position><lon>-91.93000030517578</lon><lat>39.33000183105469</lat><speedMph>570</speedMph><altitudeFt>37000</altitudeFt><source>ASDI</source><date>2013-08-08T22:53:38.000Z</date></position><position><lon>-92.0999984741211</lon><lat>39.29999923706055</lat><speedMph>572</speedMph><altitudeFt>37000</altitudeFt><source>ASDI</source><date>2013-08-08T22:52:36.000Z</date></position><position><lon>-92.30000305175781</lon><lat>39.27000045776367</lat><speedMph>571</speedMph><altitudeFt>37000</altitudeFt><source>ASDI</source><date>2013-08-08T22:51:34.000Z</date></position><position><lon>-92.47000122070312</lon><lat>39.25</lat><speedMph>570</speedMph><altitudeFt>37000</altitudeFt><source>ASDI</source><date>2013-08-08T22:50:32.000Z</date></position><position><lon>-92.6500015258789</lon><lat>39.220001220703125</lat><speedMph>572</speedMph><altitudeFt>37000</altitudeFt><source>ASDI</source><date>2013-08-08T22:49:30.000Z</date></position><position><lon>-92.81999969482422</lon><lat>39.18000030517578</lat><speedMph>571</speedMph><altitudeFt>37000</altitudeFt><source>ASDI</source><date>2013-08-08T22:48:28.000Z</date></position><position><lon>-93.0</lon><lat>39.16999816894531</lat><speedMph>566</speedMph><altitudeFt>37000</altitudeFt><source>ASDI</source><date>2013-08-08T22:47:26.000Z</date></position><position><lon>-93.19999694824219</lon><lat>39.130001068115234</lat><speedMph>565</speedMph><altitudeFt>37000</altitudeFt><source>ASDI</source><date>2013-08-08T22:46:24.000Z</date></position><position><lon>-93.37000274658203</lon><lat>39.099998474121094</lat><speedMph>564</speedMph><altitudeFt>37000</altitudeFt><source>ASDI</source><date>2013-08-08T22:45:22.000Z</date></position><position><lon>-93.52999877929688</lon><lat>39.06999969482422</lat><speedMph>568</speedMph><altitudeFt>37000</altitudeFt><source>ASDI</source><date>2013-08-08T22:44:20.000Z</date></position><position><lon>-93.72000122070312</lon><lat>39.029998779296875</lat><speedMph>570</speedMph><altitudeFt>37000</altitudeFt><source>ASDI</source><date>2013-08-08T22:43:18.000Z</date></position><position><lon>-93.87999725341797</lon><lat>39.0</lat><speedMph>571</speedMph><altitudeFt>37000</altitudeFt><source>ASDI</source><date>2013-08-08T22:42:16.000Z</date></position><position><lon>-94.08000183105469</lon><lat>38.970001220703125</lat><speedMph>566</speedMph><altitudeFt>37000</altitudeFt><source>ASDI</source><date>2013-08-08T22:41:14.000Z</date></position><position><lon>-94.2300033569336</lon><lat>38.95000076293945</lat><speedMph>567</speedMph><altitudeFt>37000</altitudeFt><source>ASDI</source><date>2013-08-08T22:40:12.000Z</date></position><position><lon>-94.43000030517578</lon><lat>38.91999816894531</lat><speedMph>565</speedMph><altitudeFt>37000</altitudeFt><source>ASDI</source><date>2013-08-08T22:39:10.000Z</date></position><position><lon>-94.5999984741211</lon><lat>38.880001068115234</lat><speedMph>565</speedMph><altitudeFt>37000</altitudeFt><source>ASDI</source><date>2013-08-08T22:38:08.000Z</date></position><position><lon>-94.77999877929688</lon><lat>38.849998474121094</lat><speedMph>566</speedMph><altitudeFt>37000</altitudeFt><source>ASDI</source><date>2013-08-08T22:37:06.000Z</date></position><position><lon>-94.94999694824219</lon><lat>38.81999969482422</lat><speedMph>565</speedMph><altitudeFt>37000</altitudeFt><source>ASDI</source><date>2013-08-08T22:36:04.000Z</date></position><position><lon>-95.12999725341797</lon><lat>38.779998779296875</lat><speedMph>559</speedMph><altitudeFt>37000</altitudeFt><source>ASDI</source><date>2013-08-08T22:35:02.000Z</date></position><position><lon>-95.30000305175781</lon><lat>38.75</lat><speedMph>563</speedMph><altitudeFt>37000</altitudeFt><source>ASDI</source><date>2013-08-08T22:34:00.000Z</date></position><position><lon>-95.4800033569336</lon><lat>38.720001220703125</lat><speedMph>567</speedMph><altitudeFt>37000</altitudeFt><source>ASDI</source><date>2013-08-08T22:32:58.000Z</date></position><position><lon>-95.6500015258789</lon><lat>38.68000030517578</lat><speedMph>558</speedMph><altitudeFt>37000</altitudeFt><source>ASDI</source><date>2013-08-08T22:31:56.000Z</date></position><position><lon>-95.83000183105469</lon><lat>38.650001525878906</lat><speedMph>571</speedMph><altitudeFt>37000</altitudeFt><source>ASDI</source><date>2013-08-08T22:30:54.000Z</date></position><position><lon>-96.0</lon><lat>38.619998931884766</lat><speedMph>571</speedMph><altitudeFt>37000</altitudeFt><source>ASDI</source><date>2013-08-08T22:29:51.000Z</date></position><position><lon>-96.18000030517578</lon><lat>38.58000183105469</lat><speedMph>574</speedMph><altitudeFt>37000</altitudeFt><source>ASDI</source><date>2013-08-08T22:28:49.000Z</date></position><position><lon>-96.3499984741211</lon><lat>38.54999923706055</lat><speedMph>575</speedMph><altitudeFt>37000</altitudeFt><source>ASDI</source><date>2013-08-08T22:27:47.000Z</date></position><position><lon>-96.52999877929688</lon><lat>38.52000045776367</lat><speedMph>571</speedMph><altitudeFt>37000</altitudeFt><source>ASDI</source><date>2013-08-08T22:26:45.000Z</date></position><position><lon>-96.69999694824219</lon><lat>38.47999954223633</lat><speedMph>562</speedMph><altitudeFt>37000</altitudeFt><source>ASDI</source><date>2013-08-08T22:25:43.000Z</date></position><position><lon>-96.87000274658203</lon><lat>38.45000076293945</lat><speedMph>565</speedMph><altitudeFt>37000</altitudeFt><source>ASDI</source><date>2013-08-08T22:24:41.000Z</date></position><position><lon>-97.06999969482422</lon><lat>38.400001525878906</lat><speedMph>565</speedMph><altitudeFt>37000</altitudeFt><source>ASDI</source><date>2013-08-08T22:23:39.000Z</date></position><position><lon>-97.2300033569336</lon><lat>38.369998931884766</lat><speedMph>565</speedMph><altitudeFt>37000</altitudeFt><source>ASDI</source><date>2013-08-08T22:22:37.000Z</date></position><position><lon>-97.41999816894531</lon><lat>38.33000183105469</lat><speedMph>568</speedMph><altitudeFt>37000</altitudeFt><source>ASDI</source><date>2013-08-08T22:21:35.000Z</date></position><position><lon>-97.58000183105469</lon><lat>38.29999923706055</lat><speedMph>566</speedMph><altitudeFt>37000</altitudeFt><source>ASDI</source><date>2013-08-08T22:20:33.000Z</date></position><position><lon>-97.75</lon><lat>38.27000045776367</lat><speedMph>564</speedMph><altitudeFt>37000</altitudeFt><source>ASDI</source><date>2013-08-08T22:19:31.000Z</date></position><position><lon>-97.91999816894531</lon><lat>38.22999954223633</lat><speedMph>564</speedMph><altitudeFt>37000</altitudeFt><source>ASDI</source><date>2013-08-08T22:18:29.000Z</date></position><position><lon>-98.08000183105469</lon><lat>38.18000030517578</lat><speedMph>560</speedMph><altitudeFt>37000</altitudeFt><source>ASDI</source><date>2013-08-08T22:17:27.000Z</date></position><position><lon>-98.25</lon><lat>38.150001525878906</lat><speedMph>559</speedMph><altitudeFt>37000</altitudeFt><source>ASDI</source><date>2013-08-08T22:16:25.000Z</date></position><position><lon>-98.44999694824219</lon><lat>38.119998931884766</lat><speedMph>562</speedMph><altitudeFt>37000</altitudeFt><source>ASDI</source><date>2013-08-08T22:15:23.000Z</date></position><position><lon>-98.62000274658203</lon><lat>38.06999969482422</lat><speedMph>562</speedMph><altitudeFt>37000</altitudeFt><source>ASDI</source><date>2013-08-08T22:14:21.000Z</date></position><position><lon>-98.77999877929688</lon><lat>38.029998779296875</lat><speedMph>564</speedMph><altitudeFt>37000</altitudeFt><source>ASDI</source><date>2013-08-08T22:13:19.000Z</date></position><position><lon>-98.94999694824219</lon><lat>38.0</lat><speedMph>566</speedMph><altitudeFt>37000</altitudeFt><source>ASDI</source><date>2013-08-08T22:12:17.000Z</date></position><position><lon>-99.12000274658203</lon><lat>37.970001220703125</lat><speedMph>566</speedMph><altitudeFt>37000</altitudeFt><source>ASDI</source><date>2013-08-08T22:11:15.000Z</date></position><position><lon>-99.27999877929688</lon><lat>37.91999816894531</lat><speedMph>566</speedMph><altitudeFt>37000</altitudeFt><source>ASDI</source><date>2013-08-08T22:10:12.000Z</date></position><position><lon>-99.44999694824219</lon><lat>37.880001068115234</lat><speedMph>567</speedMph><altitudeFt>37000</altitudeFt><source>ASDI</source><date>2013-08-08T22:09:10.000Z</date></position><position><lon>-99.62999725341797</lon><lat>37.849998474121094</lat><speedMph>568</speedMph><altitudeFt>37000</altitudeFt><source>ASDI</source><date>2013-08-08T22:08:08.000Z</date></position><position><lon>-99.80000305175781</lon><lat>37.79999923706055</lat><speedMph>572</speedMph><altitudeFt>37000</altitudeFt><source>ASDI</source><date>2013-08-08T22:07:06.000Z</date></position><position><lon>-99.9800033569336</lon><lat>37.77000045776367</lat><speedMph>573</speedMph><altitudeFt>37000</altitudeFt><source>ASDI</source><date>2013-08-08T22:06:04.000Z</date></position><position><lon>-100.12999725341797</lon><lat>37.72999954223633</lat><speedMph>570</speedMph><altitudeFt>37000</altitudeFt><source>ASDI</source><date>2013-08-08T22:05:02.000Z</date></position><position><lon>-100.31999969482422</lon><lat>37.68000030517578</lat><speedMph>572</speedMph><altitudeFt>37000</altitudeFt><source>ASDI</source><date>2013-08-08T22:04:00.000Z</date></position><position><lon>-100.5</lon><lat>37.630001068115234</lat><speedMph>567</speedMph><altitudeFt>37000</altitudeFt><source>ASDI</source><date>2013-08-08T22:02:58.000Z</date></position><position><lon>-100.66999816894531</lon><lat>37.599998474121094</lat><speedMph>583</speedMph><altitudeFt>37000</altitudeFt><source>ASDI</source><date>2013-08-08T22:01:56.000Z</date></position><position><lon>-100.83000183105469</lon><lat>37.54999923706055</lat><speedMph>577</speedMph><altitudeFt>37000</altitudeFt><source>ASDI</source><date>2013-08-08T22:00:54.000Z</date></position><position><lon>-101.0</lon><lat>37.52000045776367</lat><speedMph>572</speedMph><altitudeFt>37000</altitudeFt><source>ASDI</source><date>2013-08-08T21:59:52.000Z</date></position><position><lon>-101.18000030517578</lon><lat>37.470001220703125</lat><speedMph>578</speedMph><altitudeFt>37100</altitudeFt><source>ASDI</source><date>2013-08-08T21:58:50.000Z</date></position><position><lon>-101.3499984741211</lon><lat>37.43000030517578</lat><speedMph>578</speedMph><altitudeFt>37000</altitudeFt><source>ASDI</source><date>2013-08-08T21:57:48.000Z</date></position><position><lon>-101.52999877929688</lon><lat>37.380001068115234</lat><speedMph>574</speedMph><altitudeFt>37000</altitudeFt><source>ASDI</source><date>2013-08-08T21:56:46.000Z</date></position><position><lon>-101.69999694824219</lon><lat>37.349998474121094</lat><speedMph>571</speedMph><altitudeFt>37000</altitudeFt><source>ASDI</source><date>2013-08-08T21:55:47.000Z</date></position><position><lon>-101.69999694824219</lon><lat>37.349998474121094</lat><speedMph>571</speedMph><altitudeFt>37000</altitudeFt><source>ASDI</source><date>2013-08-08T21:55:44.000Z</date></position><position><lon>-101.8499984741211</lon><lat>37.29999923706055</lat><speedMph>572</speedMph><altitudeFt>37000</altitudeFt><source>ASDI</source><date>2013-08-08T21:54:45.000Z</date></position><position><lon>-101.8499984741211</lon><lat>37.29999923706055</lat><speedMph>570</speedMph><altitudeFt>37000</altitudeFt><source>ASDI</source><date>2013-08-08T21:54:42.000Z</date></position><position><lon>-102.02999877929688</lon><lat>37.27000045776367</lat><speedMph>578</speedMph><altitudeFt>37000</altitudeFt><source>ASDI</source><date>2013-08-08T21:53:44.000Z</date></position><position><lon>-102.02999877929688</lon><lat>37.27000045776367</lat><speedMph>571</speedMph><altitudeFt>37000</altitudeFt><source>ASDI</source><date>2013-08-08T21:53:40.000Z</date></position><position><lon>-102.19999694824219</lon><lat>37.220001220703125</lat><speedMph>579</speedMph><altitudeFt>37000</altitudeFt><source>ASDI</source><date>2013-08-08T21:52:42.000Z</date></position><position><lon>-102.19999694824219</lon><lat>37.220001220703125</lat><speedMph>575</speedMph><altitudeFt>37000</altitudeFt><source>ASDI</source><date>2013-08-08T21:52:38.000Z</date></position><position><lon>-102.3499984741211</lon><lat>37.16999816894531</lat><speedMph>585</speedMph><altitudeFt>37000</altitudeFt><source>ASDI</source><date>2013-08-08T21:51:40.000Z</date></position><position><lon>-102.37999725341797</lon><lat>37.16999816894531</lat><speedMph>580</speedMph><altitudeFt>37000</altitudeFt><source>ASDI</source><date>2013-08-08T21:51:36.000Z</date></position><position><lon>-102.52999877929688</lon><lat>37.119998931884766</lat><speedMph>587</speedMph><altitudeFt>37000</altitudeFt><source>ASDI</source><date>2013-08-08T21:50:39.000Z</date></position><position><lon>-102.52999877929688</lon><lat>37.119998931884766</lat><speedMph>583</speedMph><altitudeFt>37000</altitudeFt><source>ASDI</source><date>2013-08-08T21:50:34.000Z</date></position><position><lon>-102.68000030517578</lon><lat>37.04999923706055</lat><speedMph>589</speedMph><altitudeFt>37000</altitudeFt><source>ASDI</source><date>2013-08-08T21:49:37.000Z</date></position><position><lon>-102.72000122070312</lon><lat>37.04999923706055</lat><speedMph>589</speedMph><altitudeFt>37100</altitudeFt><source>ASDI</source><date>2013-08-08T21:49:32.000Z</date></position><position><lon>-102.87000274658203</lon><lat>36.97999954223633</lat><speedMph>592</speedMph><altitudeFt>37100</altitudeFt><source>ASDI</source><date>2013-08-08T21:48:35.000Z</date></position><position><lon>-102.87000274658203</lon><lat>36.97999954223633</lat><speedMph>578</speedMph><altitudeFt>37100</altitudeFt><source>ASDI</source><date>2013-08-08T21:48:30.000Z</date></position><position><lon>-103.02999877929688</lon><lat>36.95000076293945</lat><speedMph>571</speedMph><altitudeFt>37000</altitudeFt><source>ASDI</source><date>2013-08-08T21:47:33.000Z</date></position><position><lon>-103.05000305175781</lon><lat>36.93000030517578</lat><speedMph>571</speedMph><altitudeFt>37000</altitudeFt><source>ASDI</source><date>2013-08-08T21:47:27.000Z</date></position><position><lon>-103.22000122070312</lon><lat>36.91999816894531</lat><speedMph>562</speedMph><altitudeFt>37000</altitudeFt><source>ASDI</source><date>2013-08-08T21:46:32.000Z</date></position><position><lon>-103.22000122070312</lon><lat>36.91999816894531</lat><speedMph>564</speedMph><altitudeFt>37000</altitudeFt><source>ASDI</source><date>2013-08-08T21:46:25.000Z</date></position><position><lon>-103.37000274658203</lon><lat>36.880001068115234</lat><speedMph>560</speedMph><altitudeFt>37000</altitudeFt><source>ASDI</source><date>2013-08-08T21:45:30.000Z</date></position><position><lon>-103.4000015258789</lon><lat>36.869998931884766</lat><speedMph>558</speedMph><altitudeFt>37000</altitudeFt><source>ASDI</source><date>2013-08-08T21:45:23.000Z</date></position><position><lon>-103.55000305175781</lon><lat>36.849998474121094</lat><speedMph>557</speedMph><altitudeFt>37000</altitudeFt><source>ASDI</source><date>2013-08-08T21:44:28.000Z</date></position><position><lon>-103.55000305175781</lon><lat>36.849998474121094</lat><speedMph>558</speedMph><altitudeFt>37000</altitudeFt><source>ASDI</source><date>2013-08-08T21:44:21.000Z</date></position><position><lon>-103.69999694824219</lon><lat>36.81999969482422</lat><speedMph>560</speedMph><altitudeFt>37000</altitudeFt><source>ASDI</source><date>2013-08-08T21:43:27.000Z</date></position><position><lon>-103.7300033569336</lon><lat>36.79999923706055</lat><speedMph>562</speedMph><altitudeFt>37000</altitudeFt><source>ASDI</source><date>2013-08-08T21:43:19.000Z</date></position><position><lon>-103.87000274658203</lon><lat>36.779998779296875</lat><speedMph>557</speedMph><altitudeFt>37000</altitudeFt><source>ASDI</source><date>2013-08-08T21:42:25.000Z</date></position><position><lon>-103.9000015258789</lon><lat>36.77000045776367</lat><speedMph>560</speedMph><altitudeFt>37000</altitudeFt><source>ASDI</source><date>2013-08-08T21:42:17.000Z</date></position><position><lon>-104.05000305175781</lon><lat>36.75</lat><speedMph>556</speedMph><altitudeFt>37100</altitudeFt><source>ASDI</source><date>2013-08-08T21:41:23.000Z</date></position><position><lon>-104.05000305175781</lon><lat>36.72999954223633</lat><speedMph>559</speedMph><altitudeFt>37100</altitudeFt><source>ASDI</source><date>2013-08-08T21:41:15.000Z</date></position><position><lon>-104.19999694824219</lon><lat>36.720001220703125</lat><speedMph>549</speedMph><altitudeFt>37000</altitudeFt><source>ASDI</source><date>2013-08-08T21:40:21.000Z</date></position><position><lon>-104.22000122070312</lon><lat>36.70000076293945</lat><speedMph>554</speedMph><altitudeFt>37000</altitudeFt><source>ASDI</source><date>2013-08-08T21:40:13.000Z</date></position><position><lon>-104.37999725341797</lon><lat>36.68000030517578</lat><speedMph>547</speedMph><altitudeFt>37000</altitudeFt><source>ASDI</source><date>2013-08-08T21:39:20.000Z</date></position><position><lon>-104.41999816894531</lon><lat>36.66999816894531</lat><speedMph>545</speedMph><altitudeFt>37000</altitudeFt><source>ASDI</source><date>2013-08-08T21:39:11.000Z</date></position><position><lon>-104.55000305175781</lon><lat>36.630001068115234</lat><speedMph>554</speedMph><altitudeFt>37000</altitudeFt><source>ASDI</source><date>2013-08-08T21:38:18.000Z</date></position><position><lon>-104.56999969482422</lon><lat>36.630001068115234</lat><speedMph>559</speedMph><altitudeFt>37000</altitudeFt><source>ASDI</source><date>2013-08-08T21:38:09.000Z</date></position><position><lon>-104.72000122070312</lon><lat>36.599998474121094</lat><speedMph>550</speedMph><altitudeFt>37000</altitudeFt><source>ASDI</source><date>2013-08-08T21:37:16.000Z</date></position><position><lon>-104.87999725341797</lon><lat>36.56999969482422</lat><speedMph>543</speedMph><altitudeFt>37000</altitudeFt><source>ASDI</source><date>2013-08-08T21:36:14.000Z</date></position><position><lon>-105.02999877929688</lon><lat>36.529998779296875</lat><speedMph>542</speedMph><altitudeFt>36800</altitudeFt><source>ASDI</source><date>2013-08-08T21:35:13.000Z</date></position><position><lon>-105.19999694824219</lon><lat>36.5</lat><speedMph>542</speedMph><altitudeFt>36200</altitudeFt><source>ASDI</source><date>2013-08-08T21:34:11.000Z</date></position><position><lon>-105.3499984741211</lon><lat>36.470001220703125</lat><speedMph>541</speedMph><altitudeFt>35800</altitudeFt><source>ASDI</source><date>2013-08-08T21:33:09.000Z</date></position><position><lon>-105.5199966430664</lon><lat>36.43000030517578</lat><speedMph>542</speedMph><altitudeFt>35200</altitudeFt><source>ASDI</source><date>2013-08-08T21:32:07.000Z</date></position><position><lon>-105.66999816894531</lon><lat>36.400001525878906</lat><speedMph>544</speedMph><altitudeFt>35000</altitudeFt><source>ASDI</source><date>2013-08-08T21:31:06.000Z</date></position><position><lon>-105.83000183105469</lon><lat>36.369998931884766</lat><speedMph>547</speedMph><altitudeFt>35000</altitudeFt><source>ASDI</source><date>2013-08-08T21:30:04.000Z</date></position><position><lon>-106.0199966430664</lon><lat>36.31999969482422</lat><speedMph>549</speedMph><altitudeFt>35000</altitudeFt><source>ASDI</source><date>2013-08-08T21:29:02.000Z</date></position><position><lon>-106.18000030517578</lon><lat>36.279998779296875</lat><speedMph>541</speedMph><altitudeFt>35000</altitudeFt><source>ASDI</source><date>2013-08-08T21:28:00.000Z</date></position><position><lon>-106.33000183105469</lon><lat>36.25</lat><speedMph>541</speedMph><altitudeFt>35000</altitudeFt><source>ASDI</source><date>2013-08-08T21:26:58.000Z</date></position><position><lon>-106.4800033569336</lon><lat>36.20000076293945</lat><speedMph>539</speedMph><altitudeFt>35000</altitudeFt><source>ASDI</source><date>2013-08-08T21:25:57.000Z</date></position><position><lon>-106.6500015258789</lon><lat>36.16999816894531</lat><speedMph>539</speedMph><altitudeFt>35000</altitudeFt><source>ASDI</source><date>2013-08-08T21:24:55.000Z</date></position><position><lon>-106.80000305175781</lon><lat>36.150001525878906</lat><speedMph>537</speedMph><altitudeFt>35000</altitudeFt><source>ASDI</source><date>2013-08-08T21:23:53.000Z</date></position><position><lon>-106.94999694824219</lon><lat>36.130001068115234</lat><speedMph>541</speedMph><altitudeFt>35000</altitudeFt><source>ASDI</source><date>2013-08-08T21:22:51.000Z</date></position><position><lon>-107.12999725341797</lon><lat>36.099998474121094</lat><speedMph>542</speedMph><altitudeFt>35000</altitudeFt><source>ASDI</source><date>2013-08-08T21:21:49.000Z</date></position><position><lon>-107.27999877929688</lon><lat>36.06999969482422</lat><speedMph>541</speedMph><altitudeFt>35000</altitudeFt><source>ASDI</source><date>2013-08-08T21:20:48.000Z</date></position><position><lon>-107.44999694824219</lon><lat>36.029998779296875</lat><speedMph>542</speedMph><altitudeFt>35000</altitudeFt><source>ASDI</source><date>2013-08-08T21:19:46.000Z</date></position><position><lon>-107.5999984741211</lon><lat>36.0</lat><speedMph>540</speedMph><altitudeFt>35000</altitudeFt><source>ASDI</source><date>2013-08-08T21:18:44.000Z</date></position><position><lon>-107.77999877929688</lon><lat>35.95000076293945</lat><speedMph>537</speedMph><altitudeFt>35000</altitudeFt><source>ASDI</source><date>2013-08-08T21:17:42.000Z</date></position><position><lon>-107.91999816894531</lon><lat>35.91999816894531</lat><speedMph>539</speedMph><altitudeFt>35000</altitudeFt><source>ASDI</source><date>2013-08-08T21:16:40.000Z</date></position><position><lon>-108.0999984741211</lon><lat>35.880001068115234</lat><speedMph>539</speedMph><altitudeFt>35000</altitudeFt><source>ASDI</source><date>2013-08-08T21:15:38.000Z</date></position><position><lon>-108.25</lon><lat>35.849998474121094</lat><speedMph>537</speedMph><altitudeFt>35000</altitudeFt><source>ASDI</source><date>2013-08-08T21:14:37.000Z</date></position><position><lon>-108.41999816894531</lon><lat>35.79999923706055</lat><speedMph>537</speedMph><altitudeFt>35000</altitudeFt><source>ASDI</source><date>2013-08-08T21:13:35.000Z</date></position><position><lon>-108.56999969482422</lon><lat>35.77000045776367</lat><speedMph>539</speedMph><altitudeFt>35000</altitudeFt><source>ASDI</source><date>2013-08-08T21:12:33.000Z</date></position><position><lon>-108.7300033569336</lon><lat>35.72999954223633</lat><speedMph>539</speedMph><altitudeFt>35000</altitudeFt><source>ASDI</source><date>2013-08-08T21:11:31.000Z</date></position><position><lon>-108.87000274658203</lon><lat>35.70000076293945</lat><speedMph>541</speedMph><altitudeFt>35000</altitudeFt><source>ASDI</source><date>2013-08-08T21:10:29.000Z</date></position><position><lon>-109.05000305175781</lon><lat>35.650001525878906</lat><speedMph>541</speedMph><altitudeFt>35100</altitudeFt><source>ASDI</source><date>2013-08-08T21:09:28.000Z</date></position><position><lon>-109.18000030517578</lon><lat>35.619998931884766</lat><speedMph>542</speedMph><altitudeFt>35000</altitudeFt><source>ASDI</source><date>2013-08-08T21:08:26.000Z</date></position><position><lon>-109.37000274658203</lon><lat>35.56999969482422</lat><speedMph>542</speedMph><altitudeFt>35000</altitudeFt><source>ASDI</source><date>2013-08-08T21:07:24.000Z</date></position><position><lon>-109.5199966430664</lon><lat>35.529998779296875</lat><speedMph>536</speedMph><altitudeFt>35000</altitudeFt><source>ASDI</source><date>2013-08-08T21:06:22.000Z</date></position><position><lon>-109.6500015258789</lon><lat>35.5</lat><speedMph>539</speedMph><altitudeFt>35000</altitudeFt><source>ASDI</source><date>2013-08-08T21:05:20.000Z</date></position><position><lon>-109.81999969482422</lon><lat>35.45000076293945</lat><speedMph>540</speedMph><altitudeFt>35000</altitudeFt><source>ASDI</source><date>2013-08-08T21:04:19.000Z</date></position><position><lon>-109.97000122070312</lon><lat>35.41999816894531</lat><speedMph>541</speedMph><altitudeFt>35000</altitudeFt><source>ASDI</source><date>2013-08-08T21:03:17.000Z</date></position><position><lon>-110.12999725341797</lon><lat>35.380001068115234</lat><speedMph>541</speedMph><altitudeFt>35000</altitudeFt><source>ASDI</source><date>2013-08-08T21:02:15.000Z</date></position><position><lon>-110.27999877929688</lon><lat>35.349998474121094</lat><speedMph>543</speedMph><altitudeFt>35000</altitudeFt><source>ASDI</source><date>2013-08-08T21:01:13.000Z</date></position><position><lon>-110.47000122070312</lon><lat>35.31999969482422</lat><speedMph>547</speedMph><altitudeFt>35000</altitudeFt><source>ASDI</source><date>2013-08-08T21:00:11.000Z</date></position><position><lon>-110.62000274658203</lon><lat>35.27000045776367</lat><speedMph>543</speedMph><altitudeFt>35000</altitudeFt><source>ASDI</source><date>2013-08-08T20:59:10.000Z</date></position><position><lon>-110.77999877929688</lon><lat>35.22999954223633</lat><speedMph>543</speedMph><altitudeFt>35000</altitudeFt><source>ASDI</source><date>2013-08-08T20:58:08.000Z</date></position><position><lon>-110.93000030517578</lon><lat>35.18000030517578</lat><speedMph>543</speedMph><altitudeFt>35000</altitudeFt><source>ASDI</source><date>2013-08-08T20:57:06.000Z</date></position><position><lon>-111.06999969482422</lon><lat>35.150001525878906</lat><speedMph>547</speedMph><altitudeFt>35000</altitudeFt><source>ASDI</source><date>2013-08-08T20:56:04.000Z</date></position><position><lon>-111.25</lon><lat>35.099998474121094</lat><speedMph>544</speedMph><altitudeFt>35000</altitudeFt><source>ASDI</source><date>2013-08-08T20:55:02.000Z</date></position><position><lon>-111.4000015258789</lon><lat>35.06999969482422</lat><speedMph>547</speedMph><altitudeFt>35000</altitudeFt><source>ASDI</source><date>2013-08-08T20:54:01.000Z</date></position><position><lon>-111.55000305175781</lon><lat>35.02000045776367</lat><speedMph>550</speedMph><altitudeFt>35000</altitudeFt><source>ASDI</source><date>2013-08-08T20:52:59.000Z</date></position><position><lon>-111.72000122070312</lon><lat>34.97999954223633</lat><speedMph>549</speedMph><altitudeFt>35000</altitudeFt><source>ASDI</source><date>2013-08-08T20:51:57.000Z</date></position><position><lon>-111.87000274658203</lon><lat>34.93000030517578</lat><speedMph>545</speedMph><altitudeFt>35000</altitudeFt><source>ASDI</source><date>2013-08-08T20:50:58.000Z</date></position><position><lon>-111.87000274658203</lon><lat>34.93000030517578</lat><speedMph>547</speedMph><altitudeFt>35000</altitudeFt><source>ASDI</source><date>2013-08-08T20:50:56.000Z</date></position><position><lon>-112.0199966430664</lon><lat>34.900001525878906</lat><speedMph>545</speedMph><altitudeFt>35000</altitudeFt><source>ASDI</source><date>2013-08-08T20:49:56.000Z</date></position><position><lon>-112.05000305175781</lon><lat>34.880001068115234</lat><speedMph>544</speedMph><altitudeFt>35000</altitudeFt><source>ASDI</source><date>2013-08-08T20:49:54.000Z</date></position><position><lon>-112.19999694824219</lon><lat>34.849998474121094</lat><speedMph>543</speedMph><altitudeFt>35000</altitudeFt><source>ASDI</source><date>2013-08-08T20:48:53.000Z</date></position><position><lon>-112.19999694824219</lon><lat>34.849998474121094</lat><speedMph>543</speedMph><altitudeFt>35000</altitudeFt><source>ASDI</source><date>2013-08-08T20:48:52.000Z</date></position><position><lon>-112.3499984741211</lon><lat>34.79999923706055</lat><speedMph>544</speedMph><altitudeFt>35000</altitudeFt><source>ASDI</source><date>2013-08-08T20:47:51.000Z</date></position><position><lon>-112.3499984741211</lon><lat>34.79999923706055</lat><speedMph>543</speedMph><altitudeFt>35000</altitudeFt><source>ASDI</source><date>2013-08-08T20:47:50.000Z</date></position><position><lon>-112.5</lon><lat>34.77000045776367</lat><speedMph>547</speedMph><altitudeFt>35000</altitudeFt><source>ASDI</source><date>2013-08-08T20:46:49.000Z</date></position><position><lon>-112.5</lon><lat>34.77000045776367</lat><speedMph>545</speedMph><altitudeFt>35000</altitudeFt><source>ASDI</source><date>2013-08-08T20:46:49.000Z</date></position><position><lon>-112.6500015258789</lon><lat>34.720001220703125</lat><speedMph>548</speedMph><altitudeFt>35000</altitudeFt><source>ASDI</source><date>2013-08-08T20:45:47.000Z</date></position><position><lon>-112.81999969482422</lon><lat>34.66999816894531</lat><speedMph>550</speedMph><altitudeFt>35000</altitudeFt><source>ASDI</source><date>2013-08-08T20:44:45.000Z</date></position><position><lon>-112.81999969482422</lon><lat>34.66999816894531</lat><speedMph>551</speedMph><altitudeFt>35000</altitudeFt><source>ASDI</source><date>2013-08-08T20:44:45.000Z</date></position><position><lon>-112.97000122070312</lon><lat>34.619998931884766</lat><speedMph>552</speedMph><altitudeFt>35000</altitudeFt><source>ASDI</source><date>2013-08-08T20:43:43.000Z</date></position><position><lon>-113.12000274658203</lon><lat>34.58000183105469</lat><speedMph>557</speedMph><altitudeFt>35000</altitudeFt><source>ASDI</source><date>2013-08-08T20:42:41.000Z</date></position><position><lon>-113.12999725341797</lon><lat>34.58000183105469</lat><speedMph>555</speedMph><altitudeFt>35000</altitudeFt><source>ASDI</source><date>2013-08-08T20:42:41.000Z</date></position><position><lon>-113.27999877929688</lon><lat>34.529998779296875</lat><speedMph>554</speedMph><altitudeFt>35000</altitudeFt><source>ASDI</source><date>2013-08-08T20:41:40.000Z</date></position><position><lon>-113.27999877929688</lon><lat>34.529998779296875</lat><speedMph>555</speedMph><altitudeFt>35000</altitudeFt><source>ASDI</source><date>2013-08-08T20:41:38.000Z</date></position><position><lon>-113.43000030517578</lon><lat>34.5</lat><speedMph>549</speedMph><altitudeFt>35000</altitudeFt><source>ASDI</source><date>2013-08-08T20:40:38.000Z</date></position><position><lon>-113.43000030517578</lon><lat>34.5</lat><speedMph>550</speedMph><altitudeFt>35000</altitudeFt><source>ASDI</source><date>2013-08-08T20:40:36.000Z</date></position><position><lon>-113.62000274658203</lon><lat>34.43000030517578</lat><speedMph>549</speedMph><altitudeFt>35000</altitudeFt><source>ASDI</source><date>2013-08-08T20:39:36.000Z</date></position><position><lon>-113.62000274658203</lon><lat>34.43000030517578</lat><speedMph>552</speedMph><altitudeFt>35000</altitudeFt><source>ASDI</source><date>2013-08-08T20:39:34.000Z</date></position><position><lon>-113.75</lon><lat>34.400001525878906</lat><speedMph>551</speedMph><altitudeFt>35000</altitudeFt><source>ASDI</source><date>2013-08-08T20:38:34.000Z</date></position><position><lon>-113.7699966430664</lon><lat>34.400001525878906</lat><speedMph>564</speedMph><altitudeFt>35000</altitudeFt><source>ASDI</source><date>2013-08-08T20:38:32.000Z</date></position><position><lon>-113.91999816894531</lon><lat>34.349998474121094</lat><speedMph>552</speedMph><altitudeFt>35000</altitudeFt><source>ASDI</source><date>2013-08-08T20:37:33.000Z</date></position><position><lon>-113.91999816894531</lon><lat>34.349998474121094</lat><speedMph>549</speedMph><altitudeFt>35000</altitudeFt><source>ASDI</source><date>2013-08-08T20:37:30.000Z</date></position><position><lon>-114.06999969482422</lon><lat>34.29999923706055</lat><speedMph>548</speedMph><altitudeFt>34700</altitudeFt><source>ASDI</source><date>2013-08-08T20:36:31.000Z</date></position><position><lon>-114.06999969482422</lon><lat>34.29999923706055</lat><speedMph>548</speedMph><altitudeFt>34700</altitudeFt><source>ASDI</source><date>2013-08-08T20:36:28.000Z</date></position><position><lon>-114.22000122070312</lon><lat>34.27000045776367</lat><speedMph>547</speedMph><altitudeFt>34200</altitudeFt><source>ASDI</source><date>2013-08-08T20:35:29.000Z</date></position><position><lon>-114.2300033569336</lon><lat>34.25</lat><speedMph>548</speedMph><altitudeFt>34100</altitudeFt><source>ASDI</source><date>2013-08-08T20:35:26.000Z</date></position><position><lon>-114.37000274658203</lon><lat>34.220001220703125</lat><speedMph>549</speedMph><altitudeFt>33500</altitudeFt><source>ASDI</source><date>2013-08-08T20:34:27.000Z</date></position><position><lon>-114.37999725341797</lon><lat>34.20000076293945</lat><speedMph>543</speedMph><altitudeFt>33300</altitudeFt><source>ASDI</source><date>2013-08-08T20:34:23.000Z</date></position><position><lon>-114.5199966430664</lon><lat>34.16999816894531</lat><speedMph>551</speedMph><altitudeFt>33000</altitudeFt><source>ASDI</source><date>2013-08-08T20:33:25.000Z</date></position><position><lon>-114.52999877929688</lon><lat>34.16999816894531</lat><speedMph>543</speedMph><altitudeFt>32900</altitudeFt><source>ASDI</source><date>2013-08-08T20:33:21.000Z</date></position><position><lon>-114.66999816894531</lon><lat>34.130001068115234</lat><speedMph>551</speedMph><altitudeFt>33000</altitudeFt><source>ASDI</source><date>2013-08-08T20:32:24.000Z</date></position><position><lon>-114.68000030517578</lon><lat>34.119998931884766</lat><speedMph>543</speedMph><altitudeFt>33000</altitudeFt><source>ASDI</source><date>2013-08-08T20:32:19.000Z</date></position><position><lon>-114.83000183105469</lon><lat>34.06999969482422</lat><speedMph>547</speedMph><altitudeFt>33000</altitudeFt><source>ASDI</source><date>2013-08-08T20:31:22.000Z</date></position><position><lon>-114.83000183105469</lon><lat>34.06999969482422</lat><speedMph>544</speedMph><altitudeFt>33000</altitudeFt><source>ASDI</source><date>2013-08-08T20:31:17.000Z</date></position><position><lon>-115.0</lon><lat>34.02000045776367</lat><speedMph>545</speedMph><altitudeFt>33000</altitudeFt><source>ASDI</source><date>2013-08-08T20:30:20.000Z</date></position><position><lon>-114.9800033569336</lon><lat>34.029998779296875</lat><speedMph>548</speedMph><altitudeFt>33000</altitudeFt><source>ASDI</source><date>2013-08-08T20:30:15.000Z</date></position><position><lon>-115.12999725341797</lon><lat>33.97999954223633</lat><speedMph>544</speedMph><altitudeFt>33000</altitudeFt><source>ASDI</source><date>2013-08-08T20:29:18.000Z</date></position><position><lon>-115.16999816894531</lon><lat>33.970001220703125</lat><speedMph>548</speedMph><altitudeFt>33000</altitudeFt><source>ASDI</source><date>2013-08-08T20:29:13.000Z</date></position><position><lon>-115.27999877929688</lon><lat>33.93000030517578</lat><speedMph>542</speedMph><altitudeFt>33000</altitudeFt><source>ASDI</source><date>2013-08-08T20:28:16.000Z</date></position><position><lon>-115.31999969482422</lon><lat>33.93000030517578</lat><speedMph>548</speedMph><altitudeFt>33000</altitudeFt><source>ASDI</source><date>2013-08-08T20:28:11.000Z</date></position><position><lon>-115.43000030517578</lon><lat>33.880001068115234</lat><speedMph>545</speedMph><altitudeFt>33000</altitudeFt><source>ASDI</source><date>2013-08-08T20:27:15.000Z</date></position><position><lon>-115.47000122070312</lon><lat>33.880001068115234</lat><speedMph>549</speedMph><altitudeFt>33000</altitudeFt><source>ASDI</source><date>2013-08-08T20:27:09.000Z</date></position><position><lon>-115.58000183105469</lon><lat>33.83000183105469</lat><speedMph>549</speedMph><altitudeFt>33000</altitudeFt><source>ASDI</source><date>2013-08-08T20:26:13.000Z</date></position><position><lon>-115.62000274658203</lon><lat>33.83000183105469</lat><speedMph>548</speedMph><altitudeFt>33000</altitudeFt><source>ASDI</source><date>2013-08-08T20:26:06.000Z</date></position><position><lon>-115.7699966430664</lon><lat>33.779998779296875</lat><speedMph>547</speedMph><altitudeFt>33000</altitudeFt><source>ASDI</source><date>2013-08-08T20:25:05.000Z</date></position><position><lon>-115.9000015258789</lon><lat>33.72999954223633</lat><speedMph>533</speedMph><altitudeFt>32900</altitudeFt><source>ASDI</source><date>2013-08-08T20:24:02.000Z</date></position><position><lon>-116.08000183105469</lon><lat>33.70000076293945</lat><speedMph>529</speedMph><altitudeFt>32400</altitudeFt><source>ASDI</source><date>2013-08-08T20:23:00.000Z</date></position><position><lon>-116.2300033569336</lon><lat>33.66999816894531</lat><speedMph>531</speedMph><altitudeFt>31500</altitudeFt><source>ASDI</source><date>2013-08-08T20:21:58.000Z</date></position><position><lon>-116.37999725341797</lon><lat>33.630001068115234</lat><speedMph>556</speedMph><altitudeFt>30200</altitudeFt><source>ASDI</source><date>2013-08-08T20:20:56.000Z</date></position><position><lon>-116.55000305175781</lon><lat>33.630001068115234</lat><speedMph>549</speedMph><altitudeFt>28500</altitudeFt><source>ASDI</source><date>2013-08-08T20:19:54.000Z</date></position><position><lon>-116.69999694824219</lon><lat>33.630001068115234</lat><speedMph>542</speedMph><altitudeFt>27500</altitudeFt><source>ASDI</source><date>2013-08-08T20:18:51.000Z</date></position><position><lon>-116.87999725341797</lon><lat>33.630001068115234</lat><speedMph>535</speedMph><altitudeFt>26400</altitudeFt><source>ASDI</source><date>2013-08-08T20:17:49.000Z</date></position><position><lon>-117.02999877929688</lon><lat>33.630001068115234</lat><speedMph>534</speedMph><altitudeFt>25300</altitudeFt><source>ASDI</source><date>2013-08-08T20:16:47.000Z</date></position><position><lon>-117.18000030517578</lon><lat>33.630001068115234</lat><speedMph>527</speedMph><altitudeFt>24100</altitudeFt><source>ASDI</source><date>2013-08-08T20:15:45.000Z</date></position><position><lon>-117.33000183105469</lon><lat>33.630001068115234</lat><speedMph>507</speedMph><altitudeFt>22900</altitudeFt><source>ASDI</source><date>2013-08-08T20:14:43.000Z</date></position><position><lon>-117.5199966430664</lon><lat>33.630001068115234</lat><speedMph>493</speedMph><altitudeFt>21400</altitudeFt><source>ASDI</source><date>2013-08-08T20:13:41.000Z</date></position><position><lon>-117.68000030517578</lon><lat>33.630001068115234</lat><speedMph>478</speedMph><altitudeFt>19800</altitudeFt><source>ASDI</source><date>2013-08-08T20:12:38.000Z</date></position><position><lon>-117.80000305175781</lon><lat>33.630001068115234</lat><speedMph>463</speedMph><altitudeFt>18700</altitudeFt><source>ASDI</source><date>2013-08-08T20:11:36.000Z</date></position><position><lon>-117.93000030517578</lon><lat>33.630001068115234</lat><speedMph>457</speedMph><altitudeFt>17100</altitudeFt><source>ASDI</source><date>2013-08-08T20:10:34.000Z</date></position><position><lon>-118.06999969482422</lon><lat>33.630001068115234</lat><speedMph>442</speedMph><altitudeFt>15500</altitudeFt><source>ASDI</source><date>2013-08-08T20:09:32.000Z</date></position><position><lon>-118.22000122070312</lon><lat>33.630001068115234</lat><speedMph>426</speedMph><altitudeFt>13300</altitudeFt><source>ASDI</source><date>2013-08-08T20:08:30.000Z</date></position><position><lon>-118.33000183105469</lon><lat>33.630001068115234</lat><speedMph>381</speedMph><altitudeFt>11500</altitudeFt><source>ASDI</source><date>2013-08-08T20:07:28.000Z</date></position><position><lon>-118.43000030517578</lon><lat>33.66999816894531</lat><speedMph>345</speedMph><altitudeFt>10500</altitudeFt><source>ASDI</source><date>2013-08-08T20:06:26.000Z</date></position><position><lon>-118.5199966430664</lon><lat>33.720001220703125</lat><speedMph>312</speedMph><altitudeFt>8300</altitudeFt><source>ASDI</source><date>2013-08-08T20:05:24.000Z</date></position><position><lon>-118.5</lon><lat>33.79999923706055</lat><speedMph>305</speedMph><altitudeFt>5400</altitudeFt><source>ASDI</source><date>2013-08-08T20:04:21.000Z</date></position><position><lon>-118.4800033569336</lon><lat>33.869998931884766</lat><speedMph>275</speedMph><altitudeFt>3100</altitudeFt><source>ASDI</source><date>2013-08-08T20:03:19.000Z</date></position><position><lon>-118.47000122070312</lon><lat>33.93000030517578</lat><speedMph>191</speedMph><altitudeFt>1900</altitudeFt><source>ASDI</source><date>2013-08-08T20:02:17.000Z</date></position></positions><waypoints><waypoint><lon>-118.4000015258789</lon><lat>33.93333435058594</lat></waypoint><waypoint><lon>-118.44999694824219</lon><lat>33.93333435058594</lat></waypoint><waypoint><lon>-118.5</lon><lat>33.93333435058594</lat></waypoint><waypoint><lon>-118.5</lon><lat>33.93333435058594</lat></waypoint><waypoint><lon>-118.53333282470703</lon><lat>33.93333435058594</lat></waypoint><waypoint><lon>-118.53333282470703</lon><lat>33.93333435058594</lat></waypoint><waypoint><lon>-118.61666870117188</lon><lat>33.91666793823242</lat></waypoint><waypoint><lon>-118.61666870117188</lon><lat>33.91666793823242</lat></waypoint><waypoint><lon>-118.63333129882812</lon><lat>33.91666793823242</lat></waypoint><waypoint><lon>-118.63333129882812</lon><lat>33.900001525878906</lat></waypoint><waypoint><lon>-118.6500015258789</lon><lat>33.88333511352539</lat></waypoint><waypoint><lon>-118.6500015258789</lon><lat>33.86666488647461</lat></waypoint><waypoint><lon>-118.66666412353516</lon><lat>33.849998474121094</lat></waypoint><waypoint><lon>-118.66666412353516</lon><lat>33.79999923706055</lat></waypoint><waypoint><lon>-118.5999984741211</lon><lat>33.75</lat></waypoint><waypoint><lon>-118.5999984741211</lon><lat>33.75</lat></waypoint><waypoint><lon>-118.51667022705078</lon><lat>33.68333435058594</lat></waypoint><waypoint><lon>-118.41666412353516</lon><lat>33.66666793823242</lat></waypoint><waypoint><lon>-118.41666412353516</lon><lat>33.66666793823242</lat></waypoint><waypoint><lon>-118.33333587646484</lon><lat>33.63333511352539</lat></waypoint><waypoint><lon>-118.30000305175781</lon><lat>33.63333511352539</lat></waypoint><waypoint><lon>-118.21666717529297</lon><lat>33.63333511352539</lat></waypoint><waypoint><lon>-118.11666870117188</lon><lat>33.63333511352539</lat></waypoint><waypoint><lon>-118.06666564941406</lon><lat>33.63333511352539</lat></waypoint><waypoint><lon>-117.94999694824219</lon><lat>33.63333511352539</lat></waypoint><waypoint><lon>-117.94999694824219</lon><lat>33.63333511352539</lat></waypoint><waypoint><lon>-117.69999694824219</lon><lat>33.63333511352539</lat></waypoint><waypoint><lon>-117.5999984741211</lon><lat>33.63333511352539</lat></waypoint><waypoint><lon>-117.48332977294922</lon><lat>33.63333511352539</lat></waypoint><waypoint><lon>-117.38333129882812</lon><lat>33.63333511352539</lat></waypoint><waypoint><lon>-117.36666870117188</lon><lat>33.63333511352539</lat></waypoint><waypoint><lon>-117.01667022705078</lon><lat>33.63333511352539</lat></waypoint><waypoint><lon>-116.86666870117188</lon><lat>33.63333511352539</lat></waypoint><waypoint><lon>-116.86666870117188</lon><lat>33.63333511352539</lat></waypoint><waypoint><lon>-116.86666870117188</lon><lat>33.63333511352539</lat></waypoint><waypoint><lon>-116.5999984741211</lon><lat>33.63333511352539</lat></waypoint><waypoint><lon>-116.30000305175781</lon><lat>33.61666488647461</lat></waypoint><waypoint><lon>-116.1500015258789</lon><lat>33.61666488647461</lat></waypoint><waypoint><lon>-116.01667022705078</lon><lat>33.75</lat></waypoint><waypoint><lon>-115.96666717529297</lon><lat>33.766666412353516</lat></waypoint><waypoint><lon>-115.69999694824219</lon><lat>33.849998474121094</lat></waypoint><waypoint><lon>-115.58333587646484</lon><lat>33.88333511352539</lat></waypoint><waypoint><lon>-115.33333587646484</lon><lat>33.96666717529297</lat></waypoint><waypoint><lon>-114.0</lon><lat>34.36666488647461</lat></waypoint><waypoint><lon>-113.75</lon><lat>34.43333435058594</lat></waypoint><waypoint><lon>-113.28333282470703</lon><lat>34.56666564941406</lat></waypoint><waypoint><lon>-112.81666564941406</lon><lat>34.70000076293945</lat></waypoint><waypoint><lon>-112.58333587646484</lon><lat>34.766666412353516</lat></waypoint><waypoint><lon>-112.11666870117188</lon><lat>34.900001525878906</lat></waypoint><waypoint><lon>-111.16666412353516</lon><lat>35.150001525878906</lat></waypoint><waypoint><lon>-110.28333282470703</lon><lat>35.349998474121094</lat></waypoint><waypoint><lon>-109.8499984741211</lon><lat>35.38333511352539</lat></waypoint><waypoint><lon>-109.63333129882812</lon><lat>35.5</lat></waypoint><waypoint><lon>-107.58333587646484</lon><lat>36.0</lat></waypoint><waypoint><lon>-107.36666870117188</lon><lat>36.03333282470703</lat></waypoint><waypoint><lon>-107.18333435058594</lon><lat>36.04999923706055</lat></waypoint><waypoint><lon>-106.63333129882812</lon><lat>36.11666488647461</lat></waypoint><waypoint><lon>-106.3499984741211</lon><lat>36.18333435058594</lat></waypoint><waypoint><lon>-105.36666870117188</lon><lat>36.41666793823242</lat></waypoint><waypoint><lon>-103.55000305175781</lon><lat>36.849998474121094</lat></waypoint><waypoint><lon>-103.51667022705078</lon><lat>36.79999923706055</lat></waypoint><waypoint><lon>-102.96666717529297</lon><lat>36.96666717529297</lat></waypoint><waypoint><lon>-102.86666870117188</lon><lat>36.983333587646484</lat></waypoint><waypoint><lon>-102.30000305175781</lon><lat>37.18333435058594</lat></waypoint><waypoint><lon>-102.30000305175781</lon><lat>37.20000076293945</lat></waypoint><waypoint><lon>-101.8499984741211</lon><lat>37.29999923706055</lat></waypoint><waypoint><lon>-99.5</lon><lat>37.86666488647461</lat></waypoint><waypoint><lon>-99.26667022705078</lon><lat>37.91666793823242</lat></waypoint><waypoint><lon>-98.58333587646484</lon><lat>38.08333206176758</lat></waypoint><waypoint><lon>-97.6500015258789</lon><lat>38.28333282470703</lat></waypoint><waypoint><lon>-97.1500015258789</lon><lat>38.38333511352539</lat></waypoint><waypoint><lon>-96.0</lon><lat>38.61666488647461</lat></waypoint><waypoint><lon>-94.8499984741211</lon><lat>38.83333206176758</lat></waypoint><waypoint><lon>-94.68333435058594</lon><lat>38.86666488647461</lat></waypoint><waypoint><lon>-93.19999694824219</lon><lat>39.13333511352539</lat></waypoint><waypoint><lon>-92.21666717529297</lon><lat>39.28333282470703</lat></waypoint><waypoint><lon>-91.38333129882812</lon><lat>39.41666793823242</lat></waypoint><waypoint><lon>-90.44999694824219</lon><lat>39.54999923706055</lat></waypoint><waypoint><lon>-90.11666870117188</lon><lat>39.599998474121094</lat></waypoint><waypoint><lon>-90.01667022705078</lon><lat>39.58333206176758</lat></waypoint><waypoint><lon>-88.71666717529297</lon><lat>39.70000076293945</lat></waypoint><waypoint><lon>-88.13333129882812</lon><lat>39.71666717529297</lat></waypoint><waypoint><lon>-87.44999694824219</lon><lat>39.75</lat></waypoint><waypoint><lon>-87.18333435058594</lon><lat>39.733333587646484</lat></waypoint><waypoint><lon>-86.48332977294922</lon><lat>39.516666412353516</lat></waypoint><waypoint><lon>-86.31666564941406</lon><lat>39.46666717529297</lat></waypoint><waypoint><lon>-86.18333435058594</lon><lat>39.43333435058594</lat></waypoint><waypoint><lon>-85.78333282470703</lon><lat>39.31666564941406</lat></waypoint><waypoint><lon>-84.23332977294922</lon><lat>38.83333206176758</lat></waypoint><waypoint><lon>-84.0</lon><lat>38.75</lat></waypoint><waypoint><lon>-83.71666717529297</lon><lat>38.66666793823242</lat></waypoint><waypoint><lon>-83.66666412353516</lon><lat>38.650001525878906</lat></waypoint><waypoint><lon>-83.5</lon><lat>38.61666488647461</lat></waypoint><waypoint><lon>-83.01667022705078</lon><lat>38.54999923706055</lat></waypoint><waypoint><lon>-82.73332977294922</lon><lat>38.5</lat></waypoint><waypoint><lon>-82.63333129882812</lon><lat>38.483333587646484</lat></waypoint><waypoint><lon>-80.76667022705078</lon><lat>38.18333435058594</lat></waypoint><waypoint><lon>-79.5</lon><lat>37.96666717529297</lat></waypoint><waypoint><lon>-79.0999984741211</lon><lat>37.900001525878906</lat></waypoint><waypoint><lon>-78.81666564941406</lon><lat>37.81666564941406</lat></waypoint><waypoint><lon>-78.48332977294922</lon><lat>37.71666717529297</lat></waypoint><waypoint><lon>-78.0999984741211</lon><lat>37.599998474121094</lat></waypoint><waypoint><lon>-77.81666564941406</lon><lat>37.516666412353516</lat></waypoint><waypoint><lon>-77.69999694824219</lon><lat>37.516666412353516</lat></waypoint><waypoint><lon>-77.5999984741211</lon><lat>37.483333587646484</lat></waypoint><waypoint><lon>-77.30000305175781</lon><lat>37.483333587646484</lat></waypoint><waypoint><lon>-76.80000305175781</lon><lat>37.63333511352539</lat></waypoint><waypoint><lon>-76.3499984741211</lon><lat>37.78333282470703</lat></waypoint><waypoint><lon>-75.86666870117188</lon><lat>37.93333435058594</lat></waypoint><waypoint><lon>-75.71666717529297</lon><lat>38.06666564941406</lat></waypoint><waypoint><lon>-75.44999694824219</lon><lat>38.29999923706055</lat></waypoint><waypoint><lon>-75.1500015258789</lon><lat>38.58333206176758</lat></waypoint><waypoint><lon>-75.08333587646484</lon><lat>38.63333511352539</lat></waypoint><waypoint><lon>-75.01667022705078</lon><lat>38.733333587646484</lat></waypoint><waypoint><lon>-74.93333435058594</lon><lat>38.849998474121094</lat></waypoint><waypoint><lon>-74.80000305175781</lon><lat>39.08333206176758</lat></waypoint><waypoint><lon>-74.51667022705078</lon><lat>39.33333206176758</lat></waypoint><waypoint><lon>-74.44999694824219</lon><lat>39.400001525878906</lat></waypoint><waypoint><lon>-74.26667022705078</lon><lat>39.56666564941406</lat></waypoint><waypoint><lon>-74.26667022705078</lon><lat>39.56666564941406</lat></waypoint><waypoint><lon>-74.23332977294922</lon><lat>39.599998474121094</lat></waypoint><waypoint><lon>-74.23332977294922</lon><lat>39.29999923706055</lat></waypoint><waypoint><lon>-74.19999694824219</lon><lat>39.43333435058594</lat></waypoint><waypoint><lon>-74.36666870117188</lon><lat>39.20000076293945</lat></waypoint><waypoint><lon>-74.18333435058594</lon><lat>39.516666412353516</lat></waypoint><waypoint><lon>-74.18333435058594</lon><lat>39.56666564941406</lat></waypoint><waypoint><lon>-74.18333435058594</lon><lat>39.58333206176758</lat></waypoint><waypoint><lon>-74.16666412353516</lon><lat>39.63333511352539</lat></waypoint><waypoint><lon>-74.16666412353516</lon><lat>39.66666793823242</lat></waypoint><waypoint><lon>-74.03333282470703</lon><lat>39.78333282470703</lat></waypoint><waypoint><lon>-74.0</lon><lat>39.81666564941406</lat></waypoint><waypoint><lon>-73.98332977294922</lon><lat>39.83333206176758</lat></waypoint><waypoint><lon>-73.96666717529297</lon><lat>39.849998474121094</lat></waypoint><waypoint><lon>-73.86666870117188</lon><lat>40.0</lat></waypoint><waypoint><lon>-73.8499984741211</lon><lat>40.0</lat></waypoint><waypoint><lon>-73.8499984741211</lon><lat>40.016666412353516</lat></waypoint><waypoint><lon>-73.8499984741211</lon><lat>40.06666564941406</lat></waypoint><waypoint><lon>-73.83333587646484</lon><lat>40.099998474121094</lat></waypoint><waypoint><lon>-73.83333587646484</lon><lat>40.13333511352539</lat></waypoint><waypoint><lon>-73.83333587646484</lon><lat>40.21666717529297</lat></waypoint><waypoint><lon>-73.83333587646484</lon><lat>40.21666717529297</lat></waypoint><waypoint><lon>-73.63333129882812</lon><lat>40.29999923706055</lat></waypoint><waypoint><lon>-73.63333129882812</lon><lat>40.31666564941406</lat></waypoint><waypoint><lon>-73.6500015258789</lon><lat>40.36666488647461</lat></waypoint><waypoint><lon>-73.68333435058594</lon><lat>40.41666793823242</lat></waypoint><waypoint><lon>-73.58333587646484</lon><lat>40.36666488647461</lat></waypoint><waypoint><lon>-73.71666717529297</lon><lat>40.516666412353516</lat></waypoint><waypoint><lon>-73.76667022705078</lon><lat>40.63333511352539</lat></waypoint></waypoints><legacyRoute>KLAX./.SIE.CAMRN4.KJFK</legacyRoute></flightTrack></flightTracks><request><url>https://api.flightstats.com/flex/flightstatus/rest/v2/xml/flight/tracks/VX/406/arr/2013/8/8</url><airline><requestedCode>VX</requestedCode><fsCode>VX</fsCode></airline><flight><requested>406</requested><interpreted>406</interpreted></flight><date><year>2013</year><month>8</month><day>8</day><interpreted>2013-08-08</interpreted></date><hourOfDay><interpreted>0</interpreted></hourOfDay><numHours><interpreted>24</interpreted></numHours><utc><requested>false</requested><interpreted>false</interpreted></utc><airport/><includeFlightPlan><requested>true</requested><interpreted>true</interpreted></includeFlightPlan><maxPositions/><maxPositionAgeMinutes/><codeType/><extendedOptions/></request></response>